Workbook

Sheet Resumen
A1: Dashboard de cobranzas y facturación - Dataset ficticio
A3: Fecha de análisis | B3: 46204 | D3: Período | E3: Últimos 12 meses móviles
A5: Total facturado eq. ARS | B5: =SUM(FacturasTable[importe_equivalente_ars])
A6: Total cobrado eq. ARS | B6: =SUM(FacturasTable[importe_equivalente_ars])-SUM(FacturasTable[saldo_equivalente_ars])
A7: Saldo pendiente eq. ARS | B7: =SUM(FacturasTable[saldo_equivalente_ars])
A8: Saldo vencido eq. ARS | B8: =SUMIFS(FacturasTable[saldo_equivalente_ars],FacturasTable[estado],"Vencida")
A9: Facturas vencidas | B9: =COUNTIF(FacturasTable[estado],"Vencida")
A10: Saldo pendiente USD | B10: =SUMIFS(FacturasTable[saldo_pendiente],FacturasTable[moneda],"USD")
A11: Saldo pendiente ARS | B11: =SUMIFS(FacturasTable[saldo_pendiente],FacturasTable[moneda],"ARS")
A12: Días promedio de atraso | B12: =IFERROR(AVERAGEIF(FacturasTable[dias_atraso],">0",FacturasTable[dias_atraso]),0)
A15: Mes | B15: Facturado eq. ARS | C15: Cobrado eq. ARS | D15: Saldo eq. ARS | E15: Facturas | G15: Cliente | H15: Saldo eq. ARS | I15: Saldo USD | J15: Facturas vencidas
A16: 45870 | B16: =SUMIFS(FacturasTable[importe_equivalente_ars],FacturasTable[mes_vencimiento],A16) | C16: =SUMIFS(FacturasTable[importe_equivalente_ars],FacturasTable[mes_emision],A16)-SUMIFS(FacturasTable[saldo_equivalente_ars],FacturasTable[mes_emision],A16) | D16: =SUMIFS(FacturasTable[saldo_equivalente_ars],FacturasTable[mes_emision],A16) | E16: =COUNTIFS(FacturasTable[mes_emision],A16) | G16: Punto Sur S.A. | H16: =+SUMIF(FacturasTable[cliente],TopClientesTable[[#This Row],[Cliente]],FacturasTable[saldo_equivalente_ars]) | I16: =IF($G16="","",SUMIFS(FacturasTable[saldo_pendiente],FacturasTable[cliente],$G16,FacturasTable[moneda],"USD")) | J16: =+IF($G16="","",COUNTIFS(FacturasTable[cliente],$G16,FacturasTable[estado],"Vencida"))
A17: 45901 | B17: =SUMIFS(FacturasTable[importe_equivalente_ars],FacturasTable[mes_vencimiento],A17) | C17: =SUMIFS(FacturasTable[importe_equivalente_ars],FacturasTable[mes_emision],A17)-SUMIFS(FacturasTable[saldo_equivalente_ars],FacturasTable[mes_emision],A17) | D17: =SUMIFS(FacturasTable[saldo_equivalente_ars],FacturasTable[mes_emision],A17) | E17: =COUNTIFS(FacturasTable[mes_emision],A17) | G17: Faro Administrativo S.A.S. | H17: =+SUMIF(FacturasTable[cliente],TopClientesTable[[#This Row],[Cliente]],FacturasTable[saldo_equivalente_ars]) | I17: =IF($G17="","",SUMIFS(FacturasTable[saldo_pendiente],FacturasTable[cliente],$G17,FacturasTable[moneda],"USD")) | J17: =+IF($G17="","",COUNTIFS(FacturasTable[cliente],$G17,FacturasTable[estado],"Vencida"))
A18: 45931 | B18: =SUMIFS(FacturasTable[importe_equivalente_ars],FacturasTable[mes_vencimiento],A18) | C18: =SUMIFS(FacturasTable[importe_equivalente_ars],FacturasTable[mes_emision],A18)-SUMIFS(FacturasTable[saldo_equivalente_ars],FacturasTable[mes_emision],A18) | D18: =SUMIFS(FacturasTable[saldo_equivalente_ars],FacturasTable[mes_emision],A18) | E18: =COUNTIFS(FacturasTable[mes_emision],A18) | G18: Zonda Gestión S.R.L. | H18: =+SUMIF(FacturasTable[cliente],TopClientesTable[[#This Row],[Cliente]],FacturasTable[saldo_equivalente_ars]) | I18: =IF($G18="","",SUMIFS(FacturasTable[saldo_pendiente],FacturasTable[cliente],$G18,FacturasTable[moneda],"USD")) | J18: =+IF($G18="","",COUNTIFS(FacturasTable[cliente],$G18,FacturasTable[estado],"Vencida"))
A19: 45962 | B19: =SUMIFS(FacturasTable[importe_equivalente_ars],FacturasTable[mes_vencimiento],A19) | C19: =SUMIFS(FacturasTable[importe_equivalente_ars],FacturasTable[mes_emision],A19)-SUMIFS(FacturasTable[saldo_equivalente_ars],FacturasTable[mes_emision],A19) | D19: =SUMIFS(FacturasTable[saldo_equivalente_ars],FacturasTable[mes_emision],A19) | E19: =COUNTIFS(FacturasTable[mes_emision],A19) | G19: Eje Comercial S.R.L. | H19: =+SUMIF(FacturasTable[cliente],TopClientesTable[[#This Row],[Cliente]],FacturasTable[saldo_equivalente_ars]) | I19: =IF($G19="","",SUMIFS(FacturasTable[saldo_pendiente],FacturasTable[cliente],$G19,FacturasTable[moneda],"USD")) | J19: =+IF($G19="","",COUNTIFS(FacturasTable[cliente],$G19,FacturasTable[estado],"Vencida"))
A20: 45992 | B20: =SUMIFS(FacturasTable[importe_equivalente_ars],FacturasTable[mes_vencimiento],A20) | C20: =SUMIFS(FacturasTable[importe_equivalente_ars],FacturasTable[mes_emision],A20)-SUMIFS(FacturasTable[saldo_equivalente_ars],FacturasTable[mes_emision],A20) | D20: =SUMIFS(FacturasTable[saldo_equivalente_ars],FacturasTable[mes_emision],A20) | E20: =COUNTIFS(FacturasTable[mes_emision],A20) | G20: Litoral Soluciones S.R.L. | H20: =+SUMIF(FacturasTable[cliente],TopClientesTable[[#This Row],[Cliente]],FacturasTable[saldo_equivalente_ars]) | I20: =IF($G20="","",SUMIFS(FacturasTable[saldo_pendiente],FacturasTable[cliente],$G20,FacturasTable[moneda],"USD")) | J20: =+IF($G20="","",COUNTIFS(FacturasTable[cliente],$G20,FacturasTable[estado],"Vencida"))
A21: 46023 | B21: =SUMIFS(FacturasTable[importe_equivalente_ars],FacturasTable[mes_vencimiento],A21) | C21: =SUMIFS(FacturasTable[importe_equivalente_ars],FacturasTable[mes_emision],A21)-SUMIFS(FacturasTable[saldo_equivalente_ars],FacturasTable[mes_emision],A21) | D21: =SUMIFS(FacturasTable[saldo_equivalente_ars],FacturasTable[mes_emision],A21) | E21: =COUNTIFS(FacturasTable[mes_emision],A21) | G21: Delta Gestión PyME S.A. | H21: =+SUMIF(FacturasTable[cliente],TopClientesTable[[#This Row],[Cliente]],FacturasTable[saldo_equivalente_ars]) | I21: =IF($G21="","",SUMIFS(FacturasTable[saldo_pendiente],FacturasTable[cliente],$G21,FacturasTable[moneda],"USD")) | J21: =+IF($G21="","",COUNTIFS(FacturasTable[cliente],$G21,FacturasTable[estado],"Vencida"))
A22: 46054 | B22: =SUMIFS(FacturasTable[importe_equivalente_ars],FacturasTable[mes_vencimiento],A22) | C22: =SUMIFS(FacturasTable[importe_equivalente_ars],FacturasTable[mes_emision],A22)-SUMIFS(FacturasTable[saldo_equivalente_ars],FacturasTable[mes_emision],A22) | D22: =SUMIFS(FacturasTable[saldo_equivalente_ars],FacturasTable[mes_emision],A22) | E22: =COUNTIFS(FacturasTable[mes_emision],A22) | G22: Tango Gestión S.R.L. | H22: =+SUMIF(FacturasTable[cliente],TopClientesTable[[#This Row],[Cliente]],FacturasTable[saldo_equivalente_ars]) | I22: =IF($G22="","",SUMIFS(FacturasTable[saldo_pendiente],FacturasTable[cliente],$G22,FacturasTable[moneda],"USD")) | J22: =+IF($G22="","",COUNTIFS(FacturasTable[cliente],$G22,FacturasTable[estado],"Vencida"))
A23: 46082 | B23: =SUMIFS(FacturasTable[importe_equivalente_ars],FacturasTable[mes_vencimiento],A23) | C23: =SUMIFS(FacturasTable[importe_equivalente_ars],FacturasTable[mes_emision],A23)-SUMIFS(FacturasTable[saldo_equivalente_ars],FacturasTable[mes_emision],A23) | D23: =SUMIFS(FacturasTable[saldo_equivalente_ars],FacturasTable[mes_emision],A23) | E23: =COUNTIFS(FacturasTable[mes_emision],A23) | G23: Unión PyME Servicios S.A. | H23: =+SUMIF(FacturasTable[cliente],TopClientesTable[[#This Row],[Cliente]],FacturasTable[saldo_equivalente_ars]) | I23: =IF($G23="","",SUMIFS(FacturasTable[saldo_pendiente],FacturasTable[cliente],$G23,FacturasTable[moneda],"USD")) | J23: =+IF($G23="","",COUNTIFS(FacturasTable[cliente],$G23,FacturasTable[estado],"Vencida"))
A24: 46113 | B24: =SUMIFS(FacturasTable[importe_equivalente_ars],FacturasTable[mes_vencimiento],A24) | C24: =SUMIFS(FacturasTable[importe_equivalente_ars],FacturasTable[mes_emision],A24)-SUMIFS(FacturasTable[saldo_equivalente_ars],FacturasTable[mes_emision],A24) | D24: =SUMIFS(FacturasTable[saldo_equivalente_ars],FacturasTable[mes_emision],A24) | E24: =COUNTIFS(FacturasTable[mes_emision],A24) | G24: Valle Operativo S.R.L. | H24: =+SUMIF(FacturasTable[cliente],TopClientesTable[[#This Row],[Cliente]],FacturasTable[saldo_equivalente_ars]) | I24: =IF($G24="","",SUMIFS(FacturasTable[saldo_pendiente],FacturasTable[cliente],$G24,FacturasTable[moneda],"USD")) | J24: =+IF($G24="","",COUNTIFS(FacturasTable[cliente],$G24,FacturasTable[estado],"Vencida"))
A25: 46143 | B25: =SUMIFS(FacturasTable[importe_equivalente_ars],FacturasTable[mes_vencimiento],A25) | C25: =SUMIFS(FacturasTable[importe_equivalente_ars],FacturasTable[mes_emision],A25)-SUMIFS(FacturasTable[saldo_equivalente_ars],FacturasTable[mes_emision],A25) | D25: =SUMIFS(FacturasTable[saldo_equivalente_ars],FacturasTable[mes_emision],A25) | E25: =COUNTIFS(FacturasTable[mes_emision],A25) | G25: Horizonte Servicios S.R.L. | H25: =+SUMIF(FacturasTable[cliente],TopClientesTable[[#This Row],[Cliente]],FacturasTable[saldo_equivalente_ars]) | I25: =IF($G25="","",SUMIFS(FacturasTable[saldo_pendiente],FacturasTable[cliente],$G25,FacturasTable[moneda],"USD")) | J25: =+IF($G25="","",COUNTIFS(FacturasTable[cliente],$G25,FacturasTable[estado],"Vencida"))
A26: 46174 | B26: =SUMIFS(FacturasTable[importe_equivalente_ars],FacturasTable[mes_vencimiento],A26) | C26: =SUMIFS(FacturasTable[importe_equivalente_ars],FacturasTable[mes_emision],A26)-SUMIFS(FacturasTable[saldo_equivalente_ars],FacturasTable[mes_emision],A26) | D26: =SUMIFS(FacturasTable[saldo_equivalente_ars],FacturasTable[mes_emision],A26) | E26: =COUNTIFS(FacturasTable[mes_emision],A26)
A27: 46204 | B27: =SUMIFS(FacturasTable[importe_equivalente_ars],FacturasTable[mes_vencimiento],A27) | C27: =SUMIFS(FacturasTable[importe_equivalente_ars],FacturasTable[mes_emision],A27)-SUMIFS(FacturasTable[saldo_equivalente_ars],FacturasTable[mes_emision],A27) | D27: =SUMIFS(FacturasTable[saldo_equivalente_ars],FacturasTable[mes_emision],A27) | E27: =COUNTIFS(FacturasTable[mes_emision],A27)

Sheet Facturas
A1: id_factura | B1: fecha_emision | C1: fecha_vencimiento | D1: fecha_pago | E1: id_cliente | F1: cliente | G1: tipo_cliente | H1: id_servicio | I1: tipo_servicio | J1: moneda | K1: importe_facturado | L1: importe_cobrado | M1: saldo_pendiente | N1: tipo_cambio | O1: importe_equivalente_ars | P1: saldo_equivalente_ars | Q1: estado | R1: dias_atraso | S1: prioridad_cobranza | T1: responsable | U1: proxima_accion | V1: observaciones | W1: mes_emision | X1: mes_vencimiento | Y1: trimestre | Z1: vencida_si_no | AA1: parcial_si_no | AB1: exposicion_usd_si_no
A2: FAC-00008 | B2: 45870 | C2: 45930 | D2: 45962 | E2: CL-006 | F2: Delta Gestión PyME S.A. | G2: PyME servicios recurrentes | H2: SRV-001 | I2: Abono mensual administrativo | J2: ARS | K2: 933000 | L2: 933000 | M2: 0 | N2: 1297 | O2: 0 | P2: 0 | Q2: =IF(M9<=0,"Cobrada",IF(L9>0,"Parcial",IF(C9<Resumen!$B$3,"Vencida",IF(C9<=Resumen!$B$3+15,"Por vencer","Pendiente")))) | R2: 0 | S2: =IF(M9<=0,"Sin prioridad",IF(R9>60,"Alta",IF(R9>30,"Media",IF(C9<=Resumen!$B$3+15,"Media","Baja")))) | T2: Ana | U2: Sin acción | V2: En seguimiento administrativo | Y2: 2025-T3 | Z2: =IF(AND(M9>0,C9<Resumen!$B$3),"Sí","No") | AA2: =IF(AND(L9>0,M9>0),"Sí","No") | AB2: =IF(J9="USD","Sí","No")
A3: FAC-00022 | B3: 45876 | C3: 45891 | D3: 45899 | E3: CL-001 | F3: Altos del Centro S.R.L. | G3: PyME servicios recurrentes | H3: SRV-001 | I3: Abono mensual administrativo | J3: USD | K3: 300 | L3: 300 | M3: 0 | N3: 1297 | O3: 0 | P3: 0 | Q3: =IF(M23<=0,"Cobrada",IF(L23>0,"Parcial",IF(C23<Resumen!$B$3,"Vencida",IF(C23<=Resumen!$B$3+15,"Por vencer","Pendiente")))) | R3: 0 | S3: =IF(M23<=0,"Sin prioridad",IF(R23>60,"Alta",IF(R23>30,"Media",IF(C23<=Resumen!$B$3+15,"Media","Baja")))) | T3: Carlos | U3: Sin acción | V3: Pendiente de confirmación de pago | Y3: 2025-T3 | Z3: =IF(AND(M23>0,C23<Resumen!$B$3),"Sí","No") | AA3: =IF(AND(L23>0,M23>0),"Sí","No") | AB3: =IF(J23="USD","Sí","No")
A4: FAC-00005 | B4: 45878 | C4: 45923 | D4: 45927 | E4: CL-007 | F4: Eje Comercial S.R.L. | G4: PyME servicios recurrentes | H4: SRV-001 | I4: Abono mensual administrativo | J4: ARS | K4: 402000 | L4: 402000 | M4: 0 | N4: 1297 | O4: 0 | P4: 0 | Q4: =IF(M6<=0,"Cobrada",IF(L6>0,"Parcial",IF(C6<Resumen!$B$3,"Vencida",IF(C6<=Resumen!$B$3+15,"Por vencer","Pendiente")))) | R4: 0 | S4: =IF(M6<=0,"Sin prioridad",IF(R6>60,"Alta",IF(R6>30,"Media",IF(C6<=Resumen!$B$3+15,"Media","Baja")))) | T4: Matías | U4: Sin acción | V4: Pago prometido para próxima semana | Y4: 2025-T3 | Z4: =IF(AND(M6>0,C6<Resumen!$B$3),"Sí","No") | AA4: =IF(AND(L6>0,M6>0),"Sí","No") | AB4: =IF(J6="USD","Sí","No")
A5: FAC-00012 | B5: 45878 | C5: 45908 | D5: 45912 | E5: CL-009 | F5: Grupo Nexo PyME S.A. | G5: PyME servicios recurrentes | H5: SRV-002 | I5: Soporte operativo | J5: ARS | K5: 817000 | L5: 817000 | M5: 0 | N5: 1297 | O5: 0 | P5: 0 | Q5: =IF(M13<=0,"Cobrada",IF(L13>0,"Parcial",IF(C13<Resumen!$B$3,"Vencida",IF(C13<=Resumen!$B$3+15,"Por vencer","Pendiente")))) | R5: 0 | S5: =IF(M13<=0,"Sin prioridad",IF(R13>60,"Alta",IF(R13>30,"Media",IF(C13<=Resumen!$B$3+15,"Media","Baja")))) | T5: Ana | U5: Sin acción | Y5: 2025-T3 | Z5: =IF(AND(M13>0,C13<Resumen!$B$3),"Sí","No") | AA5: =IF(AND(L13>0,M13>0),"Sí","No") | AB5: =IF(J13="USD","Sí","No")
A6: FAC-00023 | B6: 45878 | C6: 45923 | D6: 45923 | E6: CL-014 | F6: Norte Gestión Integral S.R.L. | G6: PyME servicios recurrentes | H6: SRV-003 | I6: Consultoría de gestión | J6: USD | K6: 2300 | L6: 2300 | M6: 0 | N6: 1297 | O6: 0 | P6: 0 | Q6: =IF(M24<=0,"Cobrada",IF(L24>0,"Parcial",IF(C24<Resumen!$B$3,"Vencida",IF(C24<=Resumen!$B$3+15,"Por vencer","Pendiente")))) | R6: 0 | S6: =IF(M24<=0,"Sin prioridad",IF(R24>60,"Alta",IF(R24>30,"Media",IF(C24<=Resumen!$B$3+15,"Media","Baja")))) | T6: Carlos | U6: Sin acción | V6: Pendiente de confirmación de pago | Y6: 2025-T3 | Z6: =IF(AND(M24>0,C24<Resumen!$B$3),"Sí","No") | AA6: =IF(AND(L24>0,M24>0),"Sí","No") | AB6: =IF(J24="USD","Sí","No")
A7: FAC-00003 | B7: 45880 | C7: 45895 | D7: 45891 | E7: CL-011 | F7: Impulso Gestión S.A.S. | G7: PyME servicios recurrentes | H7: SRV-002 | I7: Soporte operativo | J7: ARS | K7: 447000 | L7: 447000 | M7: 0 | N7: 1297 | O7: 0 | P7: 0 | Q7: =IF(M4<=0,"Cobrada",IF(L4>0,"Parcial",IF(C4<Resumen!$B$3,"Vencida",IF(C4<=Resumen!$B$3+15,"Por vencer","Pendiente")))) | R7: 0 | S7: =IF(M4<=0,"Sin prioridad",IF(R4>60,"Alta",IF(R4>30,"Media",IF(C4<=Resumen!$B$3+15,"Media","Baja")))) | T7: Carlos | U7: Sin acción | V7: Cliente solicita reenvío de factura | Y7: 2025-T3 | Z7: =IF(AND(M4>0,C4<Resumen!$B$3),"Sí","No") | AA7: =IF(AND(L4>0,M4>0),"Sí","No") | AB7: =IF(J4="USD","Sí","No")
A8: FAC-00017 | B8: 45880 | C8: 45895 | D8: 45939 | E8: CL-017 | F8: Punto Sur S.A. | G8: PyME servicios recurrentes | H8: SRV-001 | I8: Abono mensual administrativo | J8: ARS | K8: 503000 | L8: 503000 | M8: 0 | N8: 1297 | O8: 0 | P8: 0 | Q8: =IF(M18<=0,"Cobrada",IF(L18>0,"Parcial",IF(C18<Resumen!$B$3,"Vencida",IF(C18<=Resumen!$B$3+15,"Por vencer","Pendiente")))) | R8: 0 | S8: =IF(M18<=0,"Sin prioridad",IF(R18>60,"Alta",IF(R18>30,"Media",IF(C18<=Resumen!$B$3+15,"Media","Baja")))) | T8: Sofía | U8: Sin acción | V8: Pago prometido para próxima semana | Y8: 2025-T3 | Z8: =IF(AND(M18>0,C18<Resumen!$B$3),"Sí","No") | AA8: =IF(AND(L18>0,M18>0),"Sí","No") | AB8: =IF(J18="USD","Sí","No")
A9: FAC-00019 | B9: 45880 | C9: 45925 | D9: 45962 | E9: CL-024 | F9: Zonda Gestión S.R.L. | G9: PyME servicios recurrentes | H9: SRV-005 | I9: Servicio extraordinario puntual | J9: ARS | K9: 742000 | L9: 299304.39 | M9: 0 | N9: 1297 | O9: 0 | P9: 0 | Q9: =IF(M20<=0,"Cobrada",IF(L20>0,"Parcial",IF(C20<Resumen!$B$3,"Vencida",IF(C20<=Resumen!$B$3+15,"Por vencer","Pendiente")))) | R9: 0 | S9: =IF(M20<=0,"Sin prioridad",IF(R20>60,"Alta",IF(R20>30,"Media",IF(C20<=Resumen!$B$3+15,"Media","Baja")))) | T9: Sofía | U9: Reclamar saldo parcial | Y9: 2025-T3 | Z9: =IF(AND(M20>0,C20<Resumen!$B$3),"Sí","No") | AA9: =IF(AND(L20>0,M20>0),"Sí","No") | AB9: =IF(J20="USD","Sí","No")
A10: FAC-00009 | B10: 45881 | C10: 45926 | E10: CL-007 | F10: Eje Comercial S.R.L. | G10: PyME servicios recurrentes | H10: SRV-002 | I10: Soporte operativo | J10: ARS | K10: 515000 | L10: 0 | M10: 0 | N10: 1297 | O10: 0 | P10: 0 | Q10: =IF(M10<=0,"Cobrada",IF(L10>0,"Parcial",IF(C10<Resumen!$B$3,"Vencida",IF(C10<=Resumen!$B$3+15,"Por vencer","Pendiente")))) | R10: 0 | S10: =IF(M10<=0,"Sin prioridad",IF(R10>60,"Alta",IF(R10>30,"Media",IF(C10<=Resumen!$B$3+15,"Media","Baja")))) | T10: Matías | U10: Escalar gestión | V10: Sin respuesta del cliente | Y10: 2025-T3 | Z10: =IF(AND(M10>0,C10<Resumen!$B$3),"Sí","No") | AA10: =IF(AND(L10>0,M10>0),"Sí","No") | AB10: =IF(J10="USD","Sí","No")
A11: FAC-00013 | B11: 45882 | C11: 45927 | D11: 45961 | E11: CL-010 | F11: Horizonte Servicios S.R.L. | G11: PyME servicios recurrentes | H11: SRV-002 | I11: Soporte operativo | J11: ARS | K11: 752000 | L11: 280330.49 | M11: 0 | N11: 1297 | O11: 0 | P11: 0 | Q11: =IF(M14<=0,"Cobrada",IF(L14>0,"Parcial",IF(C14<Resumen!$B$3,"Vencida",IF(C14<=Resumen!$B$3+15,"Por vencer","Pendiente")))) | R11: 0 | S11: =IF(M14<=0,"Sin prioridad",IF(R14>60,"Alta",IF(R14>30,"Media",IF(C14<=Resumen!$B$3+15,"Media","Baja")))) | T11: Matías | U11: Reclamar saldo parcial | V11: Pendiente de confirmación de pago | Y11: 2025-T3 | Z11: =IF(AND(M14>0,C14<Resumen!$B$3),"Sí","No") | AA11: =IF(AND(L14>0,M14>0),"Sí","No") | AB11: =IF(J14="USD","Sí","No")
A12: FAC-00014 | B12: 45882 | C12: 45897 | D12: 45914 | E12: CL-003 | F12: Arco Norte S.R.L. | G12: PyME servicios recurrentes | H12: SRV-005 | I12: Servicio extraordinario puntual | J12: ARS | K12: 1136000 | L12: 1136000 | M12: 0 | N12: 1297 | O12: 0 | P12: 0 | Q12: =IF(M15<=0,"Cobrada",IF(L15>0,"Parcial",IF(C15<Resumen!$B$3,"Vencida",IF(C15<=Resumen!$B$3+15,"Por vencer","Pendiente")))) | R12: 0 | S12: =IF(M15<=0,"Sin prioridad",IF(R15>60,"Alta",IF(R15>30,"Media",IF(C15<=Resumen!$B$3+15,"Media","Baja")))) | T12: Sofía | U12: Sin acción | V12: Pendiente de confirmación de pago | Y12: 2025-T3 | Z12: =IF(AND(M15>0,C15<Resumen!$B$3),"Sí","No") | AA12: =IF(AND(L15>0,M15>0),"Sí","No") | AB12: =IF(J15="USD","Sí","No")
A13: FAC-00020 | B13: 45882 | C13: 45897 | D13: 45909 | E13: CL-003 | F13: Arco Norte S.R.L. | G13: PyME servicios recurrentes | H13: SRV-001 | I13: Abono mensual administrativo | J13: ARS | K13: 404000 | L13: 404000 | M13: 0 | N13: 1297 | O13: 0 | P13: 0 | Q13: =IF(M21<=0,"Cobrada",IF(L21>0,"Parcial",IF(C21<Resumen!$B$3,"Vencida",IF(C21<=Resumen!$B$3+15,"Por vencer","Pendiente")))) | R13: 0 | S13: =IF(M21<=0,"Sin prioridad",IF(R21>60,"Alta",IF(R21>30,"Media",IF(C21<=Resumen!$B$3+15,"Media","Baja")))) | T13: Sofía | U13: Sin acción | V13: Sin respuesta del cliente | Y13: 2025-T3 | Z13: =IF(AND(M21>0,C21<Resumen!$B$3),"Sí","No") | AA13: =IF(AND(L21>0,M21>0),"Sí","No") | AB13: =IF(J21="USD","Sí","No")
A14: FAC-00024 | B14: 45882 | C14: 45927 | E14: CL-010 | F14: Horizonte Servicios S.R.L. | G14: PyME servicios recurrentes | H14: SRV-001 | I14: Abono mensual administrativo | J14: ARS | K14: 521000 | L14: 0 | M14: 0 | N14: 1297 | O14: 0 | P14: 0 | Q14: =IF(M25<=0,"Cobrada",IF(L25>0,"Parcial",IF(C25<Resumen!$B$3,"Vencida",IF(C25<=Resumen!$B$3+15,"Por vencer","Pendiente")))) | R14: 0 | S14: =IF(M25<=0,"Sin prioridad",IF(R25>60,"Alta",IF(R25>30,"Media",IF(C25<=Resumen!$B$3+15,"Media","Baja")))) | T14: Matías | U14: Escalar gestión | V14: Cliente solicita reenvío de factura | Y14: 2025-T3 | Z14: =IF(AND(M25>0,C25<Resumen!$B$3),"Sí","No") | AA14: =IF(AND(L25>0,M25>0),"Sí","No") | AB14: =IF(J25="USD","Sí","No")
A15: FAC-00011 | B15: 45883 | C15: 45913 | D15: 45918 | E15: CL-009 | F15: Grupo Nexo PyME S.A. | G15: PyME servicios recurrentes | H15: SRV-001 | I15: Abono mensual administrativo | J15: ARS | K15: 899000 | L15: 899000 | M15: 0 | N15: 1297 | O15: 0 | P15: 0 | Q15: =IF(M12<=0,"Cobrada",IF(L12>0,"Parcial",IF(C12<Resumen!$B$3,"Vencida",IF(C12<=Resumen!$B$3+15,"Por vencer","Pendiente")))) | R15: 0 | S15: =IF(M12<=0,"Sin prioridad",IF(R12>60,"Alta",IF(R12>30,"Media",IF(C12<=Resumen!$B$3+15,"Media","Baja")))) | T15: Ana | U15: Sin acción | Y15: 2025-T3 | Z15: =IF(AND(M12>0,C12<Resumen!$B$3),"Sí","No") | AA15: =IF(AND(L12>0,M12>0),"Sí","No") | AB15: =IF(J12="USD","Sí","No")
A16: FAC-00016 | B16: 45883 | C16: 45898 | D16: 45921 | E16: CL-017 | F16: Punto Sur S.A. | G16: PyME servicios recurrentes | H16: SRV-001 | I16: Abono mensual administrativo | J16: ARS | K16: 825000 | L16: 825000 | M16: 0 | N16: 1297 | O16: 0 | P16: 0 | Q16: =IF(M17<=0,"Cobrada",IF(L17>0,"Parcial",IF(C17<Resumen!$B$3,"Vencida",IF(C17<=Resumen!$B$3+15,"Por vencer","Pendiente")))) | R16: 0 | S16: =IF(M17<=0,"Sin prioridad",IF(R17>60,"Alta",IF(R17>30,"Media",IF(C17<=Resumen!$B$3+15,"Media","Baja")))) | T16: Sofía | U16: Sin acción | V16: Cliente solicita reenvío de factura | Y16: 2025-T3 | Z16: =IF(AND(M17>0,C17<Resumen!$B$3),"Sí","No") | AA16: =IF(AND(L17>0,M17>0),"Sí","No") | AB16: =IF(J17="USD","Sí","No")
A17: FAC-00015 | B17: 45886 | C17: 45916 | D17: 45911 | E17: CL-009 | F17: Grupo Nexo PyME S.A. | G17: PyME servicios recurrentes | H17: SRV-003 | I17: Consultoría de gestión | J17: USD | K17: 1100 | L17: 1100 | M17: 0 | N17: 1297 | O17: 0 | P17: 0 | Q17: =IF(M16<=0,"Cobrada",IF(L16>0,"Parcial",IF(C16<Resumen!$B$3,"Vencida",IF(C16<=Resumen!$B$3+15,"Por vencer","Pendiente")))) | R17: 0 | S17: =IF(M16<=0,"Sin prioridad",IF(R16>60,"Alta",IF(R16>30,"Media",IF(C16<=Resumen!$B$3+15,"Media","Baja")))) | T17: Ana | U17: Sin acción | Y17: 2025-T3 | Z17: =IF(AND(M16>0,C16<Resumen!$B$3),"Sí","No") | AA17: =IF(AND(L16>0,M16>0),"Sí","No") | AB17: =IF(J16="USD","Sí","No")
A18: FAC-00004 | B18: 45890 | C18: 45905 | D18: 45900 | E18: CL-011 | F18: Impulso Gestión S.A.S. | G18: PyME servicios recurrentes | H18: SRV-001 | I18: Abono mensual administrativo | J18: ARS | K18: 654000 | L18: 654000 | M18: 0 | N18: 1297 | O18: 0 | P18: 0 | Q18: =IF(M5<=0,"Cobrada",IF(L5>0,"Parcial",IF(C5<Resumen!$B$3,"Vencida",IF(C5<=Resumen!$B$3+15,"Por vencer","Pendiente")))) | R18: 0 | S18: =IF(M5<=0,"Sin prioridad",IF(R5>60,"Alta",IF(R5>30,"Media",IF(C5<=Resumen!$B$3+15,"Media","Baja")))) | T18: Carlos | U18: Sin acción | V18: Pago prometido para próxima semana | Y18: 2025-T3 | Z18: =IF(AND(M5>0,C5<Resumen!$B$3),"Sí","No") | AA18: =IF(AND(L5>0,M5>0),"Sí","No") | AB18: =IF(J5="USD","Sí","No")
A19: FAC-00010 | B19: 45890 | C19: 45905 | D19: 45909 | E19: CL-004 | F19: Base Sur Servicios S.A.S. | G19: PyME servicios recurrentes | H19: SRV-001 | I19: Abono mensual administrativo | J19: ARS | K19: 356000 | L19: 356000 | M19: 0 | N19: 1297 | O19: 0 | P19: 0 | Q19: =IF(M11<=0,"Cobrada",IF(L11>0,"Parcial",IF(C11<Resumen!$B$3,"Vencida",IF(C11<=Resumen!$B$3+15,"Por vencer","Pendiente")))) | R19: 0 | S19: =IF(M11<=0,"Sin prioridad",IF(R11>60,"Alta",IF(R11>30,"Media",IF(C11<=Resumen!$B$3+15,"Media","Baja")))) | T19: Ana | U19: Sin acción | Y19: 2025-T3 | Z19: =IF(AND(M11>0,C11<Resumen!$B$3),"Sí","No") | AA19: =IF(AND(L11>0,M11>0),"Sí","No") | AB19: =IF(J11="USD","Sí","No")
A20: FAC-00006 | B20: 45892 | C20: 45907 | E20: CL-023 | F20: Vector Administración S.A.S. | G20: PyME servicios recurrentes | H20: SRV-001 | I20: Abono mensual administrativo | J20: ARS | K20: 695000 | L20: 0 | M20: 0 | N20: 1297 | O20: 0 | P20: 0 | Q20: =IF(M7<=0,"Cobrada",IF(L7>0,"Parcial",IF(C7<Resumen!$B$3,"Vencida",IF(C7<=Resumen!$B$3+15,"Por vencer","Pendiente")))) | R20: 0 | S20: =IF(M7<=0,"Sin prioridad",IF(R7>60,"Alta",IF(R7>30,"Media",IF(C7<=Resumen!$B$3+15,"Media","Baja")))) | T20: Ana | U20: Llamar al cliente | V20: En seguimiento administrativo | Y20: 2025-T3 | Z20: =IF(AND(M7>0,C7<Resumen!$B$3),"Sí","No") | AA20: =IF(AND(L7>0,M7>0),"Sí","No") | AB20: =IF(J7="USD","Sí","No")
A21: FAC-00021 | B21: 45892 | C21: 45952 | E21: CL-006 | F21: Delta Gestión PyME S.A. | G21: PyME servicios recurrentes | H21: SRV-003 | I21: Consultoría de gestión | J21: ARS | K21: 1586000 | L21: 0 | M21: 0 | N21: 1297 | O21: 0 | P21: 0 | Q21: =IF(M22<=0,"Cobrada",IF(L22>0,"Parcial",IF(C22<Resumen!$B$3,"Vencida",IF(C22<=Resumen!$B$3+15,"Por vencer","Pendiente")))) | R21: 0 | S21: =IF(M22<=0,"Sin prioridad",IF(R22>60,"Alta",IF(R22>30,"Media",IF(C22<=Resumen!$B$3+15,"Media","Baja")))) | T21: Ana | U21: Reenviar factura | V21: En seguimiento administrativo | Y21: 2025-T3 | Z21: =IF(AND(M22>0,C22<Resumen!$B$3),"Sí","No") | AA21: =IF(AND(L22>0,M22>0),"Sí","No") | AB21: =IF(J22="USD","Sí","No")
A22: FAC-00002 | B22: 45894 | C22: 45909 | D22: 45924 | E22: CL-001 | F22: Altos del Centro S.R.L. | G22: PyME servicios recurrentes | H22: SRV-001 | I22: Abono mensual administrativo | J22: ARS | K22: 668000 | L22: 668000 | M22: 0 | N22: 1297 | O22: 0 | P22: 0 | Q22: =IF(M3<=0,"Cobrada",IF(L3>0,"Parcial",IF(C3<Resumen!$B$3,"Vencida",IF(C3<=Resumen!$B$3+15,"Por vencer","Pendiente")))) | R22: 0 | S22: =IF(M3<=0,"Sin prioridad",IF(R3>60,"Alta",IF(R3>30,"Media",IF(C3<=Resumen!$B$3+15,"Media","Baja")))) | T22: Carlos | U22: Sin acción | V22: Sin respuesta del cliente | Y22: 2025-T3 | Z22: =IF(AND(M3>0,C3<Resumen!$B$3),"Sí","No") | AA22: =IF(AND(L3>0,M3>0),"Sí","No") | AB22: =IF(J3="USD","Sí","No")
A23: FAC-00007 | B23: 45895 | C23: 45925 | E23: CL-008 | F23: Faro Administrativo S.A.S. | G23: PyME servicios recurrentes | H23: SRV-002 | I23: Soporte operativo | J23: ARS | K23: 643000 | L23: 0 | M23: 0 | N23: 1297 | O23: 0 | P23: 0 | Q23: =IF(M8<=0,"Cobrada",IF(L8>0,"Parcial",IF(C8<Resumen!$B$3,"Vencida",IF(C8<=Resumen!$B$3+15,"Por vencer","Pendiente")))) | R23: 0 | S23: =IF(M8<=0,"Sin prioridad",IF(R8>60,"Alta",IF(R8>30,"Media",IF(C8<=Resumen!$B$3+15,"Media","Baja")))) | T23: Sofía | U23: Reenviar factura | Y23: 2025-T3 | Z23: =IF(AND(M8>0,C8<Resumen!$B$3),"Sí","No") | AA23: =IF(AND(L8>0,M8>0),"Sí","No") | AB23: =IF(J8="USD","Sí","No")
A24: FAC-00018 | B24: 45895 | C24: 45925 | D24: 45942 | E24: CL-021 | F24: Unión PyME Servicios S.A. | G24: PyME servicios recurrentes | H24: SRV-003 | I24: Consultoría de gestión | J24: USD | K24: 1800 | L24: 1800 | M24: 0 | N24: 1297 | O24: 0 | P24: 0 | Q24: =IF(M19<=0,"Cobrada",IF(L19>0,"Parcial",IF(C19<Resumen!$B$3,"Vencida",IF(C19<=Resumen!$B$3+15,"Por vencer","Pendiente")))) | R24: 0 | S24: =IF(M19<=0,"Sin prioridad",IF(R19>60,"Alta",IF(R19>30,"Media",IF(C19<=Resumen!$B$3+15,"Media","Baja")))) | T24: Ana | U24: Sin acción | V24: Pendiente de confirmación de pago | Y24: 2025-T3 | Z24: =IF(AND(M19>0,C19<Resumen!$B$3),"Sí","No") | AA24: =IF(AND(L19>0,M19>0),"Sí","No") | AB24: =IF(J19="USD","Sí","No")
A25: FAC-00001 | B25: 45897 | C25: 45912 | D25: 45934 | E25: CL-017 | F25: Punto Sur S.A. | G25: PyME servicios recurrentes | H25: SRV-002 | I25: Soporte operativo | J25: USD | K25: 650 | L25: 650 | M25: 0 | N25: 1297 | O25: 0 | P25: 0 | Q25: =IF(M2<=0,"Cobrada",IF(L2>0,"Parcial",IF(C2<Resumen!$B$3,"Vencida",IF(C2<=Resumen!$B$3+15,"Por vencer","Pendiente")))) | R25: 0 | S25: =IF(M2<=0,"Sin prioridad",IF(R2>60,"Alta",IF(R2>30,"Media",IF(C2<=Resumen!$B$3+15,"Media","Baja")))) | T25: Sofía | U25: Sin acción | V25: En seguimiento administrativo | Y25: 2025-T3 | Z25: =IF(AND(M2>0,C2<Resumen!$B$3),"Sí","No") | AA25: =IF(AND(L2>0,M2>0),"Sí","No") | AB25: =IF(J2="USD","Sí","No")
A26: FAC-00033 | B26: 45902 | C26: 45947 | D26: 45950 | E26: CL-018 | F26: Río Claro Servicios S.R.L. | G26: PyME servicios recurrentes | H26: SRV-002 | I26: Soporte operativo | J26: USD | K26: 250 | L26: 250 | M26: 0 | N26: 1330 | O26: 0 | P26: 0 | Q26: =IF(M34<=0,"Cobrada",IF(L34>0,"Parcial",IF(C34<Resumen!$B$3,"Vencida",IF(C34<=Resumen!$B$3+15,"Por vencer","Pendiente")))) | R26: 0 | S26: =IF(M34<=0,"Sin prioridad",IF(R34>60,"Alta",IF(R34>30,"Media",IF(C34<=Resumen!$B$3+15,"Media","Baja")))) | T26: Ana | U26: Sin acción | V26: En seguimiento administrativo | Y26: 2025-T3 | Z26: =IF(AND(M34>0,C34<Resumen!$B$3),"Sí","No") | AA26: =IF(AND(L34>0,M34>0),"Sí","No") | AB26: =IF(J34="USD","Sí","No")
A27: FAC-00044 | B27: 45902 | C27: 45932 | D27: 45932 | E27: CL-009 | F27: Grupo Nexo PyME S.A. | G27: PyME servicios recurrentes | H27: SRV-001 | I27: Abono mensual administrativo | J27: ARS | K27: 926000 | L27: 926000 | M27: 0 | N27: 1330 | O27: 0 | P27: 0 | Q27: =IF(M45<=0,"Cobrada",IF(L45>0,"Parcial",IF(C45<Resumen!$B$3,"Vencida",IF(C45<=Resumen!$B$3+15,"Por vencer","Pendiente")))) | R27: 0 | S27: =IF(M45<=0,"Sin prioridad",IF(R45>60,"Alta",IF(R45>30,"Media",IF(C45<=Resumen!$B$3+15,"Media","Baja")))) | T27: Ana | U27: Sin acción | V27: En seguimiento administrativo | Y27: 2025-T3 | Z27: =IF(AND(M45>0,C45<Resumen!$B$3),"Sí","No") | AA27: =IF(AND(L45>0,M45>0),"Sí","No") | AB27: =IF(J45="USD","Sí","No")
A28: FAC-00031 | B28: 45903 | C28: 45918 | D28: 45934 | E28: CL-017 | F28: Punto Sur S.A. | G28: PyME servicios recurrentes | H28: SRV-001 | I28: Abono mensual administrativo | J28: ARS | K28: 405000 | L28: 405000 | M28: 0 | N28: 1330 | O28: 0 | P28: 0 | Q28: =IF(M32<=0,"Cobrada",IF(L32>0,"Parcial",IF(C32<Resumen!$B$3,"Vencida",IF(C32<=Resumen!$B$3+15,"Por vencer","Pendiente")))) | R28: 0 | S28: =IF(M32<=0,"Sin prioridad",IF(R32>60,"Alta",IF(R32>30,"Media",IF(C32<=Resumen!$B$3+15,"Media","Baja")))) | T28: Sofía | U28: Sin acción | V28: En seguimiento administrativo | Y28: 2025-T3 | Z28: =IF(AND(M32>0,C32<Resumen!$B$3),"Sí","No") | AA28: =IF(AND(L32>0,M32>0),"Sí","No") | AB28: =IF(J32="USD","Sí","No")
A29: FAC-00029 | B29: 45906 | C29: 45936 | D29: 45959 | E29: CL-019 | F29: Sierra Norte S.A.S. | G29: PyME servicios recurrentes | H29: SRV-001 | I29: Abono mensual administrativo | J29: ARS | K29: 942000 | L29: 268010.92 | M29: 0 | N29: 1330 | O29: 0 | P29: 0 | Q29: =IF(M30<=0,"Cobrada",IF(L30>0,"Parcial",IF(C30<Resumen!$B$3,"Vencida",IF(C30<=Resumen!$B$3+15,"Por vencer","Pendiente")))) | R29: 0 | S29: =IF(M30<=0,"Sin prioridad",IF(R30>60,"Alta",IF(R30>30,"Media",IF(C30<=Resumen!$B$3+15,"Media","Baja")))) | T29: Carlos | U29: Reclamar saldo parcial | V29: Sin respuesta del cliente | Y29: 2025-T3 | Z29: =IF(AND(M30>0,C30<Resumen!$B$3),"Sí","No") | AA29: =IF(AND(L30>0,M30>0),"Sí","No") | AB29: =IF(J30="USD","Sí","No")
A30: FAC-00047 | B30: 45906 | C30: 45921 | E30: CL-023 | F30: Vector Administración S.A.S. | G30: PyME servicios recurrentes | H30: SRV-001 | I30: Abono mensual administrativo | J30: USD | K30: 750 | L30: 0 | M30: 0 | N30: 1330 | O30: 0 | P30: 0 | Q30: =IF(M48<=0,"Cobrada",IF(L48>0,"Parcial",IF(C48<Resumen!$B$3,"Vencida",IF(C48<=Resumen!$B$3+15,"Por vencer","Pendiente")))) | R30: 0 | S30: =IF(M48<=0,"Sin prioridad",IF(R48>60,"Alta",IF(R48>30,"Media",IF(C48<=Resumen!$B$3+15,"Media","Baja")))) | T30: Ana | U30: Llamar al cliente | Y30: 2025-T3 | Z30: =IF(AND(M48>0,C48<Resumen!$B$3),"Sí","No") | AA30: =IF(AND(L48>0,M48>0),"Sí","No") | AB30: =IF(J48="USD","Sí","No")
A31: FAC-00035 | B31: 45907 | C31: 45922 | D31: 45949 | E31: CL-017 | F31: Punto Sur S.A. | G31: PyME servicios recurrentes | H31: SRV-003 | I31: Consultoría de gestión | J31: USD | K31: 1700 | L31: 1700 | M31: 0 | N31: 1330 | O31: 0 | P31: 0 | Q31: =IF(M36<=0,"Cobrada",IF(L36>0,"Parcial",IF(C36<Resumen!$B$3,"Vencida",IF(C36<=Resumen!$B$3+15,"Por vencer","Pendiente")))) | R31: 0 | S31: =IF(M36<=0,"Sin prioridad",IF(R36>60,"Alta",IF(R36>30,"Media",IF(C36<=Resumen!$B$3+15,"Media","Baja")))) | T31: Sofía | U31: Sin acción | V31: Pendiente de confirmación de pago | Y31: 2025-T3 | Z31: =IF(AND(M36>0,C36<Resumen!$B$3),"Sí","No") | AA31: =IF(AND(L36>0,M36>0),"Sí","No") | AB31: =IF(J36="USD","Sí","No")
A32: FAC-00037 | B32: 45907 | C32: 45952 | D32: 45953 | E32: CL-018 | F32: Río Claro Servicios S.R.L. | G32: PyME servicios recurrentes | H32: SRV-001 | I32: Abono mensual administrativo | J32: ARS | K32: 821000 | L32: 821000 | M32: 0 | N32: 1330 | O32: 0 | P32: 0 | Q32: =IF(M38<=0,"Cobrada",IF(L38>0,"Parcial",IF(C38<Resumen!$B$3,"Vencida",IF(C38<=Resumen!$B$3+15,"Por vencer","Pendiente")))) | R32: 0 | S32: =IF(M38<=0,"Sin prioridad",IF(R38>60,"Alta",IF(R38>30,"Media",IF(C38<=Resumen!$B$3+15,"Media","Baja")))) | T32: Ana | U32: Sin acción | V32: Pendiente de confirmación de pago | Y32: 2025-T3 | Z32: =IF(AND(M38>0,C38<Resumen!$B$3),"Sí","No") | AA32: =IF(AND(L38>0,M38>0),"Sí","No") | AB32: =IF(J38="USD","Sí","No")
A33: FAC-00040 | B33: 45907 | C33: 45937 | D33: 45946 | E33: CL-019 | F33: Sierra Norte S.A.S. | G33: PyME servicios recurrentes | H33: SRV-002 | I33: Soporte operativo | J33: ARS | K33: 367000 | L33: 367000 | M33: 0 | N33: 1330 | O33: 0 | P33: 0 | Q33: =IF(M41<=0,"Cobrada",IF(L41>0,"Parcial",IF(C41<Resumen!$B$3,"Vencida",IF(C41<=Resumen!$B$3+15,"Por vencer","Pendiente")))) | R33: 0 | S33: =IF(M41<=0,"Sin prioridad",IF(R41>60,"Alta",IF(R41>30,"Media",IF(C41<=Resumen!$B$3+15,"Media","Baja")))) | T33: Carlos | U33: Sin acción | V33: Sin respuesta del cliente | Y33: 2025-T3 | Z33: =IF(AND(M41>0,C41<Resumen!$B$3),"Sí","No") | AA33: =IF(AND(L41>0,M41>0),"Sí","No") | AB33: =IF(J41="USD","Sí","No")
A34: FAC-00042 | B34: 45908 | C34: 45938 | D34: 45959 | E34: CL-008 | F34: Faro Administrativo S.A.S. | G34: PyME servicios recurrentes | H34: SRV-003 | I34: Consultoría de gestión | J34: USD | K34: 2400 | L34: 2400 | M34: 0 | N34: 1330 | O34: 0 | P34: 0 | Q34: =IF(M43<=0,"Cobrada",IF(L43>0,"Parcial",IF(C43<Resumen!$B$3,"Vencida",IF(C43<=Resumen!$B$3+15,"Por vencer","Pendiente")))) | R34: 0 | S34: =IF(M43<=0,"Sin prioridad",IF(R43>60,"Alta",IF(R43>30,"Media",IF(C43<=Resumen!$B$3+15,"Media","Baja")))) | T34: Sofía | U34: Sin acción | V34: En seguimiento administrativo | Y34: 2025-T3 | Z34: =IF(AND(M43>0,C43<Resumen!$B$3),"Sí","No") | AA34: =IF(AND(L43>0,M43>0),"Sí","No") | AB34: =IF(J43="USD","Sí","No")
A35: FAC-00027 | B35: 45909 | C35: 45954 | D35: 45990 | E35: CL-010 | F35: Horizonte Servicios S.R.L. | G35: PyME servicios recurrentes | H35: SRV-001 | I35: Abono mensual administrativo | J35: ARS | K35: 808000 | L35: 808000 | M35: 0 | N35: 1330 | O35: 0 | P35: 0 | Q35: =IF(M28<=0,"Cobrada",IF(L28>0,"Parcial",IF(C28<Resumen!$B$3,"Vencida",IF(C28<=Resumen!$B$3+15,"Por vencer","Pendiente")))) | R35: 0 | S35: =IF(M28<=0,"Sin prioridad",IF(R28>60,"Alta",IF(R28>30,"Media",IF(C28<=Resumen!$B$3+15,"Media","Baja")))) | T35: Matías | U35: Sin acción | V35: Cliente solicita reenvío de factura | Y35: 2025-T3 | Z35: =IF(AND(M28>0,C28<Resumen!$B$3),"Sí","No") | AA35: =IF(AND(L28>0,M28>0),"Sí","No") | AB35: =IF(J28="USD","Sí","No")
A36: FAC-00036 | B36: 45909 | C36: 45954 | D36: 45967 | E36: CL-007 | F36: Eje Comercial S.R.L. | G36: PyME servicios recurrentes | H36: SRV-001 | I36: Abono mensual administrativo | J36: ARS | K36: 912000 | L36: 912000 | M36: 0 | N36: 1330 | O36: 0 | P36: 0 | Q36: =IF(M37<=0,"Cobrada",IF(L37>0,"Parcial",IF(C37<Resumen!$B$3,"Vencida",IF(C37<=Resumen!$B$3+15,"Por vencer","Pendiente")))) | R36: 0 | S36: =IF(M37<=0,"Sin prioridad",IF(R37>60,"Alta",IF(R37>30,"Media",IF(C37<=Resumen!$B$3+15,"Media","Baja")))) | T36: Matías | U36: Sin acción | V36: Sin respuesta del cliente | Y36: 2025-T3 | Z36: =IF(AND(M37>0,C37<Resumen!$B$3),"Sí","No") | AA36: =IF(AND(L37>0,M37>0),"Sí","No") | AB36: =IF(J37="USD","Sí","No")
A37: FAC-00041 | B37: 45909 | C37: 45939 | D37: 45956 | E37: CL-008 | F37: Faro Administrativo S.A.S. | G37: PyME servicios recurrentes | H37: SRV-001 | I37: Abono mensual administrativo | J37: USD | K37: 850 | L37: 850 | M37: 0 | N37: 1330 | O37: 0 | P37: 0 | Q37: =IF(M42<=0,"Cobrada",IF(L42>0,"Parcial",IF(C42<Resumen!$B$3,"Vencida",IF(C42<=Resumen!$B$3+15,"Por vencer","Pendiente")))) | R37: 0 | S37: =IF(M42<=0,"Sin prioridad",IF(R42>60,"Alta",IF(R42>30,"Media",IF(C42<=Resumen!$B$3+15,"Media","Baja")))) | T37: Sofía | U37: Sin acción | V37: En seguimiento administrativo | Y37: 2025-T3 | Z37: =IF(AND(M42>0,C42<Resumen!$B$3),"Sí","No") | AA37: =IF(AND(L42>0,M42>0),"Sí","No") | AB37: =IF(J42="USD","Sí","No")
A38: FAC-00025 | B38: 45910 | C38: 45955 | E38: CL-016 | F38: Patagonia Gestión S.R.L. | G38: PyME servicios recurrentes | H38: SRV-001 | I38: Abono mensual administrativo | J38: ARS | K38: 817000 | L38: 0 | M38: 0 | N38: 1330 | O38: 0 | P38: 0 | Q38: =IF(M26<=0,"Cobrada",IF(L26>0,"Parcial",IF(C26<Resumen!$B$3,"Vencida",IF(C26<=Resumen!$B$3+15,"Por vencer","Pendiente")))) | R38: 0 | S38: =IF(M26<=0,"Sin prioridad",IF(R26>60,"Alta",IF(R26>30,"Media",IF(C26<=Resumen!$B$3+15,"Media","Baja")))) | T38: Matías | U38: Reenviar factura | Y38: 2025-T3 | Z38: =IF(AND(M26>0,C26<Resumen!$B$3),"Sí","No") | AA38: =IF(AND(L26>0,M26>0),"Sí","No") | AB38: =IF(J26="USD","Sí","No")
A39: FAC-00038 | B39: 45911 | C39: 45956 | E39: CL-007 | F39: Eje Comercial S.R.L. | G39: PyME servicios recurrentes | H39: SRV-004 | I39: Reporte mensual / tablero de control | J39: USD | K39: 1300 | L39: 0 | M39: 0 | N39: 1330 | O39: 0 | P39: 0 | Q39: =IF(M39<=0,"Cobrada",IF(L39>0,"Parcial",IF(C39<Resumen!$B$3,"Vencida",IF(C39<=Resumen!$B$3+15,"Por vencer","Pendiente")))) | R39: 0 | S39: =IF(M39<=0,"Sin prioridad",IF(R39>60,"Alta",IF(R39>30,"Media",IF(C39<=Resumen!$B$3+15,"Media","Baja")))) | T39: Matías | U39: Reenviar factura | V39: Pago prometido para próxima semana | Y39: 2025-T3 | Z39: =IF(AND(M39>0,C39<Resumen!$B$3),"Sí","No") | AA39: =IF(AND(L39>0,M39>0),"Sí","No") | AB39: =IF(J39="USD","Sí","No")
A40: FAC-00043 | B40: 45913 | C40: 45928 | D40: 45932 | E40: CL-011 | F40: Impulso Gestión S.A.S. | G40: PyME servicios recurrentes | H40: SRV-001 | I40: Abono mensual administrativo | J40: ARS | K40: 926000 | L40: 926000 | M40: 0 | N40: 1330 | O40: 0 | P40: 0 | Q40: =IF(M44<=0,"Cobrada",IF(L44>0,"Parcial",IF(C44<Resumen!$B$3,"Vencida",IF(C44<=Resumen!$B$3+15,"Por vencer","Pendiente")))) | R40: 0 | S40: =IF(M44<=0,"Sin prioridad",IF(R44>60,"Alta",IF(R44>30,"Media",IF(C44<=Resumen!$B$3+15,"Media","Baja")))) | T40: Carlos | U40: Sin acción | V40: Cliente solicita reenvío de factura | Y40: 2025-T3 | Z40: =IF(AND(M44>0,C44<Resumen!$B$3),"Sí","No") | AA40: =IF(AND(L44>0,M44>0),"Sí","No") | AB40: =IF(J44="USD","Sí","No")
A41: FAC-00046 | B41: 45914 | C41: 45959 | D41: 45991 | E41: CL-024 | F41: Zonda Gestión S.R.L. | G41: PyME servicios recurrentes | H41: SRV-003 | I41: Consultoría de gestión | J41: ARS | K41: 1004000 | L41: 1004000 | M41: 0 | N41: 1330 | O41: 0 | P41: 0 | Q41: =IF(M47<=0,"Cobrada",IF(L47>0,"Parcial",IF(C47<Resumen!$B$3,"Vencida",IF(C47<=Resumen!$B$3+15,"Por vencer","Pendiente")))) | R41: 0 | S41: =IF(M47<=0,"Sin prioridad",IF(R47>60,"Alta",IF(R47>30,"Media",IF(C47<=Resumen!$B$3+15,"Media","Baja")))) | T41: Sofía | U41: Sin acción | V41: Sin respuesta del cliente | Y41: 2025-T3 | Z41: =IF(AND(M47>0,C47<Resumen!$B$3),"Sí","No") | AA41: =IF(AND(L47>0,M47>0),"Sí","No") | AB41: =IF(J47="USD","Sí","No")
A42: FAC-00048 | B42: 45914 | C42: 45959 | D42: 45972 | E42: CL-012 | F42: Litoral Soluciones S.R.L. | G42: PyME servicios recurrentes | H42: SRV-002 | I42: Soporte operativo | J42: ARS | K42: 832000 | L42: 214547.43 | M42: 0 | N42: 1330 | O42: 0 | P42: 0 | Q42: =IF(M49<=0,"Cobrada",IF(L49>0,"Parcial",IF(C49<Resumen!$B$3,"Vencida",IF(C49<=Resumen!$B$3+15,"Por vencer","Pendiente")))) | R42: 0 | S42: =IF(M49<=0,"Sin prioridad",IF(R49>60,"Alta",IF(R49>30,"Media",IF(C49<=Resumen!$B$3+15,"Media","Baja")))) | T42: Matías | U42: Reclamar saldo parcial | V42: Sin respuesta del cliente | Y42: 2025-T3 | Z42: =IF(AND(M49>0,C49<Resumen!$B$3),"Sí","No") | AA42: =IF(AND(L49>0,M49>0),"Sí","No") | AB42: =IF(J49="USD","Sí","No")
A43: FAC-00032 | B43: 45916 | C43: 45931 | D43: 45931 | E43: CL-011 | F43: Impulso Gestión S.A.S. | G43: PyME servicios recurrentes | H43: SRV-004 | I43: Reporte mensual / tablero de control | J43: ARS | K43: 916000 | L43: 916000 | M43: 0 | N43: 1330 | O43: 0 | P43: 0 | Q43: =IF(M33<=0,"Cobrada",IF(L33>0,"Parcial",IF(C33<Resumen!$B$3,"Vencida",IF(C33<=Resumen!$B$3+15,"Por vencer","Pendiente")))) | R43: 0 | S43: =IF(M33<=0,"Sin prioridad",IF(R33>60,"Alta",IF(R33>30,"Media",IF(C33<=Resumen!$B$3+15,"Media","Baja")))) | T43: Carlos | U43: Sin acción | V43: Sin respuesta del cliente | Y43: 2025-T3 | Z43: =IF(AND(M33>0,C33<Resumen!$B$3),"Sí","No") | AA43: =IF(AND(L33>0,M33>0),"Sí","No") | AB43: =IF(J33="USD","Sí","No")
A44: FAC-00045 | B44: 45916 | C44: 45946 | D44: 45954 | E44: CL-021 | F44: Unión PyME Servicios S.A. | G44: PyME servicios recurrentes | H44: SRV-005 | I44: Servicio extraordinario puntual | J44: ARS | K44: 1180000 | L44: 1180000 | M44: 0 | N44: 1330 | O44: 0 | P44: 0 | Q44: =IF(M46<=0,"Cobrada",IF(L46>0,"Parcial",IF(C46<Resumen!$B$3,"Vencida",IF(C46<=Resumen!$B$3+15,"Por vencer","Pendiente")))) | R44: 0 | S44: =IF(M46<=0,"Sin prioridad",IF(R46>60,"Alta",IF(R46>30,"Media",IF(C46<=Resumen!$B$3+15,"Media","Baja")))) | T44: Ana | U44: Sin acción | V44: Pago prometido para próxima semana | Y44: 2025-T3 | Z44: =IF(AND(M46>0,C46<Resumen!$B$3),"Sí","No") | AA44: =IF(AND(L46>0,M46>0),"Sí","No") | AB44: =IF(J46="USD","Sí","No")
A45: FAC-00034 | B45: 45919 | C45: 45949 | D45: 45986 | E45: CL-008 | F45: Faro Administrativo S.A.S. | G45: PyME servicios recurrentes | H45: SRV-003 | I45: Consultoría de gestión | J45: USD | K45: 1750 | L45: 1750 | M45: 0 | N45: 1330 | O45: 0 | P45: 0 | Q45: =IF(M35<=0,"Cobrada",IF(L35>0,"Parcial",IF(C35<Resumen!$B$3,"Vencida",IF(C35<=Resumen!$B$3+15,"Por vencer","Pendiente")))) | R45: 0 | S45: =IF(M35<=0,"Sin prioridad",IF(R35>60,"Alta",IF(R35>30,"Media",IF(C35<=Resumen!$B$3+15,"Media","Baja")))) | T45: Sofía | U45: Sin acción | V45: En seguimiento administrativo | Y45: 2025-T3 | Z45: =IF(AND(M35>0,C35<Resumen!$B$3),"Sí","No") | AA45: =IF(AND(L35>0,M35>0),"Sí","No") | AB45: =IF(J35="USD","Sí","No")
A46: FAC-00028 | B46: 45921 | C46: 45936 | D46: 45949 | E46: CL-001 | F46: Altos del Centro S.R.L. | G46: PyME servicios recurrentes | H46: SRV-001 | I46: Abono mensual administrativo | J46: ARS | K46: 690000 | L46: 690000 | M46: 0 | N46: 1330 | O46: 0 | P46: 0 | Q46: =IF(M29<=0,"Cobrada",IF(L29>0,"Parcial",IF(C29<Resumen!$B$3,"Vencida",IF(C29<=Resumen!$B$3+15,"Por vencer","Pendiente")))) | R46: 0 | S46: =IF(M29<=0,"Sin prioridad",IF(R29>60,"Alta",IF(R29>30,"Media",IF(C29<=Resumen!$B$3+15,"Media","Baja")))) | T46: Carlos | U46: Sin acción | V46: En seguimiento administrativo | Y46: 2025-T3 | Z46: =IF(AND(M29>0,C29<Resumen!$B$3),"Sí","No") | AA46: =IF(AND(L29>0,M29>0),"Sí","No") | AB46: =IF(J29="USD","Sí","No")
A47: FAC-00030 | B47: 45923 | C47: 45968 | D47: 45974 | E47: CL-016 | F47: Patagonia Gestión S.R.L. | G47: PyME servicios recurrentes | H47: SRV-001 | I47: Abono mensual administrativo | J47: USD | K47: 700 | L47: 700 | M47: 0 | N47: 1330 | O47: 0 | P47: 0 | Q47: =IF(M31<=0,"Cobrada",IF(L31>0,"Parcial",IF(C31<Resumen!$B$3,"Vencida",IF(C31<=Resumen!$B$3+15,"Por vencer","Pendiente")))) | R47: 0 | S47: =IF(M31<=0,"Sin prioridad",IF(R31>60,"Alta",IF(R31>30,"Media",IF(C31<=Resumen!$B$3+15,"Media","Baja")))) | T47: Matías | U47: Sin acción | V47: Pendiente de confirmación de pago | Y47: 2025-T3 | Z47: =IF(AND(M31>0,C31<Resumen!$B$3),"Sí","No") | AA47: =IF(AND(L31>0,M31>0),"Sí","No") | AB47: =IF(J31="USD","Sí","No")
A48: FAC-00049 | B48: 45925 | C48: 45940 | D48: 45949 | E48: CL-015 | F48: Órbita Servicios S.A.S. | G48: PyME servicios recurrentes | H48: SRV-002 | I48: Soporte operativo | J48: ARS | K48: 534000 | L48: 534000 | M48: 0 | N48: 1330 | O48: 0 | P48: 0 | Q48: =IF(M50<=0,"Cobrada",IF(L50>0,"Parcial",IF(C50<Resumen!$B$3,"Vencida",IF(C50<=Resumen!$B$3+15,"Por vencer","Pendiente")))) | R48: 0 | S48: =IF(M50<=0,"Sin prioridad",IF(R50>60,"Alta",IF(R50>30,"Media",IF(C50<=Resumen!$B$3+15,"Media","Baja")))) | T48: Matías | U48: Sin acción | V48: Pago prometido para próxima semana | Y48: 2025-T3 | Z48: =IF(AND(M50>0,C50<Resumen!$B$3),"Sí","No") | AA48: =IF(AND(L50>0,M50>0),"Sí","No") | AB48: =IF(J50="USD","Sí","No")
A49: FAC-00026 | B49: 45927 | C49: 45957 | D49: 45971 | E49: CL-019 | F49: Sierra Norte S.A.S. | G49: PyME servicios recurrentes | H49: SRV-001 | I49: Abono mensual administrativo | J49: ARS | K49: 533000 | L49: 533000 | M49: 0 | N49: 1330 | O49: 0 | P49: 0 | Q49: =IF(M27<=0,"Cobrada",IF(L27>0,"Parcial",IF(C27<Resumen!$B$3,"Vencida",IF(C27<=Resumen!$B$3+15,"Por vencer","Pendiente")))) | R49: 0 | S49: =IF(M27<=0,"Sin prioridad",IF(R27>60,"Alta",IF(R27>30,"Media",IF(C27<=Resumen!$B$3+15,"Media","Baja")))) | T49: Carlos | U49: Sin acción | V49: Pago prometido para próxima semana | Y49: 2025-T3 | Z49: =IF(AND(M27>0,C27<Resumen!$B$3),"Sí","No") | AA49: =IF(AND(L27>0,M27>0),"Sí","No") | AB49: =IF(J27="USD","Sí","No")
A50: FAC-00039 | B50: 45927 | C50: 45957 | E50: CL-019 | F50: Sierra Norte S.A.S. | G50: PyME servicios recurrentes | H50: SRV-002 | I50: Soporte operativo | J50: USD | K50: 750 | L50: 0 | M50: 0 | N50: 1330 | O50: 0 | P50: 0 | Q50: =IF(M40<=0,"Cobrada",IF(L40>0,"Parcial",IF(C40<Resumen!$B$3,"Vencida",IF(C40<=Resumen!$B$3+15,"Por vencer","Pendiente")))) | R50: 0 | S50: =IF(M40<=0,"Sin prioridad",IF(R40>60,"Alta",IF(R40>30,"Media",IF(C40<=Resumen!$B$3+15,"Media","Baja")))) | T50: Carlos | U50: Reenviar factura | V50: Sin respuesta del cliente | Y50: 2025-T3 | Z50: =IF(AND(M40>0,C40<Resumen!$B$3),"Sí","No") | AA50: =IF(AND(L40>0,M40>0),"Sí","No") | AB50: =IF(J40="USD","Sí","No")
A51: FAC-00055 | B51: 45932 | C51: 45977 | D51: 45977 | E51: CL-014 | F51: Norte Gestión Integral S.R.L. | G51: PyME servicios recurrentes | H51: SRV-004 | I51: Reporte mensual / tablero de control | J51: USD | K51: 1400 | L51: 1400 | M51: 0 | N51: 1354 | O51: 0 | P51: 0 | Q51: =IF(M56<=0,"Cobrada",IF(L56>0,"Parcial",IF(C56<Resumen!$B$3,"Vencida",IF(C56<=Resumen!$B$3+15,"Por vencer","Pendiente")))) | R51: 0 | S51: =IF(M56<=0,"Sin prioridad",IF(R56>60,"Alta",IF(R56>30,"Media",IF(C56<=Resumen!$B$3+15,"Media","Baja")))) | T51: Carlos | U51: Sin acción | V51: Sin respuesta del cliente | Y51: 2025-T4 | Z51: =IF(AND(M56>0,C56<Resumen!$B$3),"Sí","No") | AA51: =IF(AND(L56>0,M56>0),"Sí","No") | AB51: =IF(J56="USD","Sí","No")
A52: FAC-00058 | B52: 45935 | C52: 45965 | D52: 45969 | E52: CL-019 | F52: Sierra Norte S.A.S. | G52: PyME servicios recurrentes | H52: SRV-001 | I52: Abono mensual administrativo | J52: ARS | K52: 630000 | L52: 630000 | M52: 0 | N52: 1354 | O52: 0 | P52: 0 | Q52: =IF(M59<=0,"Cobrada",IF(L59>0,"Parcial",IF(C59<Resumen!$B$3,"Vencida",IF(C59<=Resumen!$B$3+15,"Por vencer","Pendiente")))) | R52: 0 | S52: =IF(M59<=0,"Sin prioridad",IF(R59>60,"Alta",IF(R59>30,"Media",IF(C59<=Resumen!$B$3+15,"Media","Baja")))) | T52: Carlos | U52: Sin acción | V52: Sin respuesta del cliente | Y52: 2025-T4 | Z52: =IF(AND(M59>0,C59<Resumen!$B$3),"Sí","No") | AA52: =IF(AND(L59>0,M59>0),"Sí","No") | AB52: =IF(J59="USD","Sí","No")
A53: FAC-00065 | B53: 45937 | C53: 45982 | E53: CL-024 | F53: Zonda Gestión S.R.L. | G53: PyME servicios recurrentes | H53: SRV-002 | I53: Soporte operativo | J53: ARS | K53: 458000 | L53: 0 | M53: 0 | N53: 1354 | O53: 0 | P53: 0 | Q53: =IF(M66<=0,"Cobrada",IF(L66>0,"Parcial",IF(C66<Resumen!$B$3,"Vencida",IF(C66<=Resumen!$B$3+15,"Por vencer","Pendiente")))) | R53: 0 | S53: =IF(M66<=0,"Sin prioridad",IF(R66>60,"Alta",IF(R66>30,"Media",IF(C66<=Resumen!$B$3+15,"Media","Baja")))) | T53: Sofía | U53: Reenviar factura | V53: Sin respuesta del cliente | Y53: 2025-T4 | Z53: =IF(AND(M66>0,C66<Resumen!$B$3),"Sí","No") | AA53: =IF(AND(L66>0,M66>0),"Sí","No") | AB53: =IF(J66="USD","Sí","No")
A54: FAC-00062 | B54: 45938 | C54: 45968 | D54: 45984 | E54: CL-021 | F54: Unión PyME Servicios S.A. | G54: PyME servicios recurrentes | H54: SRV-004 | I54: Reporte mensual / tablero de control | J54: USD | K54: 1050 | L54: 380.57 | M54: 0 | N54: 1354 | O54: 0 | P54: 0 | Q54: =IF(M63<=0,"Cobrada",IF(L63>0,"Parcial",IF(C63<Resumen!$B$3,"Vencida",IF(C63<=Resumen!$B$3+15,"Por vencer","Pendiente")))) | R54: 0 | S54: =IF(M63<=0,"Sin prioridad",IF(R63>60,"Alta",IF(R63>30,"Media",IF(C63<=Resumen!$B$3+15,"Media","Baja")))) | T54: Ana | U54: Reclamar saldo parcial | V54: Sin respuesta del cliente | Y54: 2025-T4 | Z54: =IF(AND(M63>0,C63<Resumen!$B$3),"Sí","No") | AA54: =IF(AND(L63>0,M63>0),"Sí","No") | AB54: =IF(J63="USD","Sí","No")
A55: FAC-00066 | B55: 45938 | C55: 45983 | D55: 46017 | E55: CL-024 | F55: Zonda Gestión S.R.L. | G55: PyME servicios recurrentes | H55: SRV-001 | I55: Abono mensual administrativo | J55: ARS | K55: 406000 | L55: 176121.31 | M55: 0 | N55: 1354 | O55: 0 | P55: 0 | Q55: =IF(M67<=0,"Cobrada",IF(L67>0,"Parcial",IF(C67<Resumen!$B$3,"Vencida",IF(C67<=Resumen!$B$3+15,"Por vencer","Pendiente")))) | R55: 0 | S55: =IF(M67<=0,"Sin prioridad",IF(R67>60,"Alta",IF(R67>30,"Media",IF(C67<=Resumen!$B$3+15,"Media","Baja")))) | T55: Sofía | U55: Reclamar saldo parcial | V55: En seguimiento administrativo | Y55: 2025-T4 | Z55: =IF(AND(M67>0,C67<Resumen!$B$3),"Sí","No") | AA55: =IF(AND(L67>0,M67>0),"Sí","No") | AB55: =IF(J67="USD","Sí","No")
A56: FAC-00064 | B56: 45940 | C56: 45955 | D56: 45974 | E56: CL-013 | F56: Mercurio PyME S.A. | G56: PyME servicios recurrentes | H56: SRV-001 | I56: Abono mensual administrativo | J56: ARS | K56: 388000 | L56: 154883.98 | M56: 0 | N56: 1354 | O56: 0 | P56: 0 | Q56: =IF(M65<=0,"Cobrada",IF(L65>0,"Parcial",IF(C65<Resumen!$B$3,"Vencida",IF(C65<=Resumen!$B$3+15,"Por vencer","Pendiente")))) | R56: 0 | S56: =IF(M65<=0,"Sin prioridad",IF(R65>60,"Alta",IF(R65>30,"Media",IF(C65<=Resumen!$B$3+15,"Media","Baja")))) | T56: Sofía | U56: Reclamar saldo parcial | V56: En seguimiento administrativo | Y56: 2025-T4 | Z56: =IF(AND(M65>0,C65<Resumen!$B$3),"Sí","No") | AA56: =IF(AND(L65>0,M65>0),"Sí","No") | AB56: =IF(J65="USD","Sí","No")
A57: FAC-00056 | B57: 45942 | C57: 45987 | D57: 46017 | E57: CL-024 | F57: Zonda Gestión S.R.L. | G57: PyME servicios recurrentes | H57: SRV-001 | I57: Abono mensual administrativo | J57: ARS | K57: 435000 | L57: 435000 | M57: 0 | N57: 1354 | O57: 0 | P57: 0 | Q57: =IF(M57<=0,"Cobrada",IF(L57>0,"Parcial",IF(C57<Resumen!$B$3,"Vencida",IF(C57<=Resumen!$B$3+15,"Por vencer","Pendiente")))) | R57: 0 | S57: =IF(M57<=0,"Sin prioridad",IF(R57>60,"Alta",IF(R57>30,"Media",IF(C57<=Resumen!$B$3+15,"Media","Baja")))) | T57: Sofía | U57: Sin acción | V57: Cliente solicita reenvío de factura | Y57: 2025-T4 | Z57: =IF(AND(M57>0,C57<Resumen!$B$3),"Sí","No") | AA57: =IF(AND(L57>0,M57>0),"Sí","No") | AB57: =IF(J57="USD","Sí","No")
A58: FAC-00057 | B58: 45942 | C58: 45957 | D58: 45969 | E58: CL-023 | F58: Vector Administración S.A.S. | G58: PyME servicios recurrentes | H58: SRV-002 | I58: Soporte operativo | J58: ARS | K58: 746000 | L58: 746000 | M58: 0 | N58: 1354 | O58: 0 | P58: 0 | Q58: =IF(M58<=0,"Cobrada",IF(L58>0,"Parcial",IF(C58<Resumen!$B$3,"Vencida",IF(C58<=Resumen!$B$3+15,"Por vencer","Pendiente")))) | R58: 0 | S58: =IF(M58<=0,"Sin prioridad",IF(R58>60,"Alta",IF(R58>30,"Media",IF(C58<=Resumen!$B$3+15,"Media","Baja")))) | T58: Ana | U58: Sin acción | V58: Cliente solicita reenvío de factura | Y58: 2025-T4 | Z58: =IF(AND(M58>0,C58<Resumen!$B$3),"Sí","No") | AA58: =IF(AND(L58>0,M58>0),"Sí","No") | AB58: =IF(J58="USD","Sí","No")
A59: FAC-00050 | B59: 45947 | C59: 45962 | D59: 45963 | E59: CL-005 | F59: Cerro Azul S.R.L. | G59: PyME servicios recurrentes | H59: SRV-001 | I59: Abono mensual administrativo | J59: ARS | K59: 898000 | L59: 898000 | M59: 0 | N59: 1354 | O59: 0 | P59: 0 | Q59: =IF(M51<=0,"Cobrada",IF(L51>0,"Parcial",IF(C51<Resumen!$B$3,"Vencida",IF(C51<=Resumen!$B$3+15,"Por vencer","Pendiente")))) | R59: 0 | S59: =IF(M51<=0,"Sin prioridad",IF(R51>60,"Alta",IF(R51>30,"Media",IF(C51<=Resumen!$B$3+15,"Media","Baja")))) | T59: Ana | U59: Sin acción | V59: En seguimiento administrativo | Y59: 2025-T4 | Z59: =IF(AND(M51>0,C51<Resumen!$B$3),"Sí","No") | AA59: =IF(AND(L51>0,M51>0),"Sí","No") | AB59: =IF(J51="USD","Sí","No")
A60: FAC-00067 | B60: 45949 | C60: 45964 | D60: 45980 | E60: CL-001 | F60: Altos del Centro S.R.L. | G60: PyME servicios recurrentes | H60: SRV-005 | I60: Servicio extraordinario puntual | J60: ARS | K60: 1197000 | L60: 1197000 | M60: 0 | N60: 1354 | O60: 0 | P60: 0 | Q60: =IF(M68<=0,"Cobrada",IF(L68>0,"Parcial",IF(C68<Resumen!$B$3,"Vencida",IF(C68<=Resumen!$B$3+15,"Por vencer","Pendiente")))) | R60: 0 | S60: =IF(M68<=0,"Sin prioridad",IF(R68>60,"Alta",IF(R68>30,"Media",IF(C68<=Resumen!$B$3+15,"Media","Baja")))) | T60: Carlos | U60: Sin acción | V60: En seguimiento administrativo | Y60: 2025-T4 | Z60: =IF(AND(M68>0,C68<Resumen!$B$3),"Sí","No") | AA60: =IF(AND(L68>0,M68>0),"Sí","No") | AB60: =IF(J68="USD","Sí","No")
A61: FAC-00052 | B61: 45952 | C61: 45967 | D61: 45973 | E61: CL-015 | F61: Órbita Servicios S.A.S. | G61: PyME servicios recurrentes | H61: SRV-003 | I61: Consultoría de gestión | J61: USD | K61: 1250 | L61: 1250 | M61: 0 | N61: 1354 | O61: 0 | P61: 0 | Q61: =IF(M53<=0,"Cobrada",IF(L53>0,"Parcial",IF(C53<Resumen!$B$3,"Vencida",IF(C53<=Resumen!$B$3+15,"Por vencer","Pendiente")))) | R61: 0 | S61: =IF(M53<=0,"Sin prioridad",IF(R53>60,"Alta",IF(R53>30,"Media",IF(C53<=Resumen!$B$3+15,"Media","Baja")))) | T61: Matías | U61: Sin acción | V61: Pendiente de confirmación de pago | Y61: 2025-T4 | Z61: =IF(AND(M53>0,C53<Resumen!$B$3),"Sí","No") | AA61: =IF(AND(L53>0,M53>0),"Sí","No") | AB61: =IF(J53="USD","Sí","No")
A62: FAC-00060 | B62: 45952 | C62: 45967 | D62: 45972 | E62: CL-015 | F62: Órbita Servicios S.A.S. | G62: PyME servicios recurrentes | H62: SRV-004 | I62: Reporte mensual / tablero de control | J62: USD | K62: 550 | L62: 550 | M62: 0 | N62: 1354 | O62: 0 | P62: 0 | Q62: =IF(M61<=0,"Cobrada",IF(L61>0,"Parcial",IF(C61<Resumen!$B$3,"Vencida",IF(C61<=Resumen!$B$3+15,"Por vencer","Pendiente")))) | R62: 0 | S62: =IF(M61<=0,"Sin prioridad",IF(R61>60,"Alta",IF(R61>30,"Media",IF(C61<=Resumen!$B$3+15,"Media","Baja")))) | T62: Matías | U62: Sin acción | Y62: 2025-T4 | Z62: =IF(AND(M61>0,C61<Resumen!$B$3),"Sí","No") | AA62: =IF(AND(L61>0,M61>0),"Sí","No") | AB62: =IF(J61="USD","Sí","No")
A63: FAC-00061 | B63: 45952 | C63: 45967 | E63: CL-020 | F63: Tango Gestión S.R.L. | G63: PyME servicios recurrentes | H63: SRV-004 | I63: Reporte mensual / tablero de control | J63: USD | K63: 1000 | L63: 0 | M63: 0 | N63: 1354 | O63: 0 | P63: 0 | Q63: =IF(M62<=0,"Cobrada",IF(L62>0,"Parcial",IF(C62<Resumen!$B$3,"Vencida",IF(C62<=Resumen!$B$3+15,"Por vencer","Pendiente")))) | R63: 0 | S63: =IF(M62<=0,"Sin prioridad",IF(R62>60,"Alta",IF(R62>30,"Media",IF(C62<=Resumen!$B$3+15,"Media","Baja")))) | T63: Ana | U63: Reenviar factura | Y63: 2025-T4 | Z63: =IF(AND(M62>0,C62<Resumen!$B$3),"Sí","No") | AA63: =IF(AND(L62>0,M62>0),"Sí","No") | AB63: =IF(J62="USD","Sí","No")
A64: FAC-00051 | B64: 45953 | C64: 45998 | D64: 45994 | E64: CL-014 | F64: Norte Gestión Integral S.R.L. | G64: PyME servicios recurrentes | H64: SRV-001 | I64: Abono mensual administrativo | J64: ARS | K64: 801000 | L64: 801000 | M64: 0 | N64: 1354 | O64: 0 | P64: 0 | Q64: =IF(M52<=0,"Cobrada",IF(L52>0,"Parcial",IF(C52<Resumen!$B$3,"Vencida",IF(C52<=Resumen!$B$3+15,"Por vencer","Pendiente")))) | R64: 0 | S64: =IF(M52<=0,"Sin prioridad",IF(R52>60,"Alta",IF(R52>30,"Media",IF(C52<=Resumen!$B$3+15,"Media","Baja")))) | T64: Carlos | U64: Sin acción | V64: En seguimiento administrativo | Y64: 2025-T4 | Z64: =IF(AND(M52>0,C52<Resumen!$B$3),"Sí","No") | AA64: =IF(AND(L52>0,M52>0),"Sí","No") | AB64: =IF(J52="USD","Sí","No")
A65: FAC-00053 | B65: 45953 | C65: 45968 | D65: 45987 | E65: CL-020 | F65: Tango Gestión S.R.L. | G65: PyME servicios recurrentes | H65: SRV-001 | I65: Abono mensual administrativo | J65: USD | K65: 500 | L65: 500 | M65: 0 | N65: 1354 | O65: 0 | P65: 0 | Q65: =IF(M54<=0,"Cobrada",IF(L54>0,"Parcial",IF(C54<Resumen!$B$3,"Vencida",IF(C54<=Resumen!$B$3+15,"Por vencer","Pendiente")))) | R65: 0 | S65: =IF(M54<=0,"Sin prioridad",IF(R54>60,"Alta",IF(R54>30,"Media",IF(C54<=Resumen!$B$3+15,"Media","Baja")))) | T65: Ana | U65: Sin acción | V65: Pago prometido para próxima semana | Y65: 2025-T4 | Z65: =IF(AND(M54>0,C54<Resumen!$B$3),"Sí","No") | AA65: =IF(AND(L54>0,M54>0),"Sí","No") | AB65: =IF(J54="USD","Sí","No")
A66: FAC-00054 | B66: 45953 | C66: 45968 | D66: 45972 | E66: CL-011 | F66: Impulso Gestión S.A.S. | G66: PyME servicios recurrentes | H66: SRV-005 | I66: Servicio extraordinario puntual | J66: ARS | K66: 715000 | L66: 715000 | M66: 0 | N66: 1354 | O66: 0 | P66: 0 | Q66: =IF(M55<=0,"Cobrada",IF(L55>0,"Parcial",IF(C55<Resumen!$B$3,"Vencida",IF(C55<=Resumen!$B$3+15,"Por vencer","Pendiente")))) | R66: 0 | S66: =IF(M55<=0,"Sin prioridad",IF(R55>60,"Alta",IF(R55>30,"Media",IF(C55<=Resumen!$B$3+15,"Media","Baja")))) | T66: Carlos | U66: Sin acción | V66: Pendiente de confirmación de pago | Y66: 2025-T4 | Z66: =IF(AND(M55>0,C55<Resumen!$B$3),"Sí","No") | AA66: =IF(AND(L55>0,M55>0),"Sí","No") | AB66: =IF(J55="USD","Sí","No")
A67: FAC-00063 | B67: 45954 | C67: 45984 | E67: CL-009 | F67: Grupo Nexo PyME S.A. | G67: PyME servicios recurrentes | H67: SRV-001 | I67: Abono mensual administrativo | J67: ARS | K67: 591000 | L67: 0 | M67: 0 | N67: 1354 | O67: 0 | P67: 0 | Q67: =IF(M64<=0,"Cobrada",IF(L64>0,"Parcial",IF(C64<Resumen!$B$3,"Vencida",IF(C64<=Resumen!$B$3+15,"Por vencer","Pendiente")))) | R67: 0 | S67: =IF(M64<=0,"Sin prioridad",IF(R64>60,"Alta",IF(R64>30,"Media",IF(C64<=Resumen!$B$3+15,"Media","Baja")))) | T67: Ana | U67: Enviar recordatorio | V67: Pago prometido para próxima semana | Y67: 2025-T4 | Z67: =IF(AND(M64>0,C64<Resumen!$B$3),"Sí","No") | AA67: =IF(AND(L64>0,M64>0),"Sí","No") | AB67: =IF(J64="USD","Sí","No")
A68: FAC-00059 | B68: 45957 | C68: 46002 | E68: CL-022 | F68: Valle Operativo S.R.L. | G68: PyME servicios recurrentes | H68: SRV-001 | I68: Abono mensual administrativo | J68: ARS | K68: 776000 | L68: 0 | M68: 0 | N68: 1354 | O68: 0 | P68: 0 | Q68: =IF(M60<=0,"Cobrada",IF(L60>0,"Parcial",IF(C60<Resumen!$B$3,"Vencida",IF(C60<=Resumen!$B$3+15,"Por vencer","Pendiente")))) | R68: 0 | S68: =IF(M60<=0,"Sin prioridad",IF(R60>60,"Alta",IF(R60>30,"Media",IF(C60<=Resumen!$B$3+15,"Media","Baja")))) | T68: Ana | U68: Enviar recordatorio | V68: Sin respuesta del cliente | Y68: 2025-T4 | Z68: =IF(AND(M60>0,C60<Resumen!$B$3),"Sí","No") | AA68: =IF(AND(L60>0,M60>0),"Sí","No") | AB68: =IF(J60="USD","Sí","No")
A69: FAC-00073 | B69: 45967 | C69: 46012 | D69: 46032 | E69: CL-012 | F69: Litoral Soluciones S.R.L. | G69: PyME servicios recurrentes | H69: SRV-004 | I69: Reporte mensual / tablero de control | J69: USD | K69: 1150 | L69: 780.4 | M69: 0 | N69: 1398 | O69: 0 | P69: 0 | Q69: =IF(M74<=0,"Cobrada",IF(L74>0,"Parcial",IF(C74<Resumen!$B$3,"Vencida",IF(C74<=Resumen!$B$3+15,"Por vencer","Pendiente")))) | R69: 0 | S69: =IF(M74<=0,"Sin prioridad",IF(R74>60,"Alta",IF(R74>30,"Media",IF(C74<=Resumen!$B$3+15,"Media","Baja")))) | T69: Matías | U69: Reclamar saldo parcial | Y69: 2025-T4 | Z69: =IF(AND(M74>0,C74<Resumen!$B$3),"Sí","No") | AA69: =IF(AND(L74>0,M74>0),"Sí","No") | AB69: =IF(J74="USD","Sí","No")
A70: FAC-00084 | B70: 45968 | C70: 45983 | E70: CL-020 | F70: Tango Gestión S.R.L. | G70: PyME servicios recurrentes | H70: SRV-002 | I70: Soporte operativo | J70: USD | K70: 600 | L70: 0 | M70: 0 | N70: 1398 | O70: 0 | P70: 0 | Q70: =IF(M85<=0,"Cobrada",IF(L85>0,"Parcial",IF(C85<Resumen!$B$3,"Vencida",IF(C85<=Resumen!$B$3+15,"Por vencer","Pendiente")))) | R70: 0 | S70: =IF(M85<=0,"Sin prioridad",IF(R85>60,"Alta",IF(R85>30,"Media",IF(C85<=Resumen!$B$3+15,"Media","Baja")))) | T70: Ana | U70: Reenviar factura | V70: Sin respuesta del cliente | Y70: 2025-T4 | Z70: =IF(AND(M85>0,C85<Resumen!$B$3),"Sí","No") | AA70: =IF(AND(L85>0,M85>0),"Sí","No") | AB70: =IF(J85="USD","Sí","No")
A71: FAC-00091 | B71: 45968 | C71: 45998 | D71: 46012 | E71: CL-021 | F71: Unión PyME Servicios S.A. | G71: PyME servicios recurrentes | H71: SRV-001 | I71: Abono mensual administrativo | J71: ARS | K71: 545000 | L71: 545000 | M71: 0 | N71: 1398 | O71: 0 | P71: 0 | Q71: =IF(M92<=0,"Cobrada",IF(L92>0,"Parcial",IF(C92<Resumen!$B$3,"Vencida",IF(C92<=Resumen!$B$3+15,"Por vencer","Pendiente")))) | R71: 0 | S71: =IF(M92<=0,"Sin prioridad",IF(R92>60,"Alta",IF(R92>30,"Media",IF(C92<=Resumen!$B$3+15,"Media","Baja")))) | T71: Ana | U71: Sin acción | V71: Pago prometido para próxima semana | Y71: 2025-T4 | Z71: =IF(AND(M92>0,C92<Resumen!$B$3),"Sí","No") | AA71: =IF(AND(L92>0,M92>0),"Sí","No") | AB71: =IF(J92="USD","Sí","No")
A72: FAC-00075 | B72: 45969 | C72: 46014 | D72: 46092 | E72: CL-010 | F72: Horizonte Servicios S.R.L. | G72: PyME servicios recurrentes | H72: SRV-001 | I72: Abono mensual administrativo | J72: USD | K72: 650 | L72: 650 | M72: 0 | N72: 1398 | O72: 0 | P72: 0 | Q72: =IF(M76<=0,"Cobrada",IF(L76>0,"Parcial",IF(C76<Resumen!$B$3,"Vencida",IF(C76<=Resumen!$B$3+15,"Por vencer","Pendiente")))) | R72: 0 | S72: =IF(M76<=0,"Sin prioridad",IF(R76>60,"Alta",IF(R76>30,"Media",IF(C76<=Resumen!$B$3+15,"Media","Baja")))) | T72: Matías | U72: Sin acción | Y72: 2025-T4 | Z72: =IF(AND(M76>0,C76<Resumen!$B$3),"Sí","No") | AA72: =IF(AND(L76>0,M76>0),"Sí","No") | AB72: =IF(J76="USD","Sí","No")
A73: FAC-00082 | B73: 45970 | C73: 45985 | E73: CL-003 | F73: Arco Norte S.R.L. | G73: PyME servicios recurrentes | H73: SRV-004 | I73: Reporte mensual / tablero de control | J73: USD | K73: 950 | L73: 0 | M73: 0 | N73: 1398 | O73: 0 | P73: 0 | Q73: =IF(M83<=0,"Cobrada",IF(L83>0,"Parcial",IF(C83<Resumen!$B$3,"Vencida",IF(C83<=Resumen!$B$3+15,"Por vencer","Pendiente")))) | R73: 0 | S73: =IF(M83<=0,"Sin prioridad",IF(R83>60,"Alta",IF(R83>30,"Media",IF(C83<=Resumen!$B$3+15,"Media","Baja")))) | T73: Sofía | U73: Enviar recordatorio | Y73: 2025-T4 | Z73: =IF(AND(M83>0,C83<Resumen!$B$3),"Sí","No") | AA73: =IF(AND(L83>0,M83>0),"Sí","No") | AB73: =IF(J83="USD","Sí","No")
A74: FAC-00079 | B74: 45972 | C74: 46017 | D74: 46024 | E74: CL-007 | F74: Eje Comercial S.R.L. | G74: PyME servicios recurrentes | H74: SRV-005 | I74: Servicio extraordinario puntual | J74: ARS | K74: 975000 | L74: 975000 | M74: 0 | N74: 1398 | O74: 0 | P74: 0 | Q74: =IF(M80<=0,"Cobrada",IF(L80>0,"Parcial",IF(C80<Resumen!$B$3,"Vencida",IF(C80<=Resumen!$B$3+15,"Por vencer","Pendiente")))) | R74: 0 | S74: =IF(M80<=0,"Sin prioridad",IF(R80>60,"Alta",IF(R80>30,"Media",IF(C80<=Resumen!$B$3+15,"Media","Baja")))) | T74: Matías | U74: Sin acción | V74: Cliente solicita reenvío de factura | Y74: 2025-T4 | Z74: =IF(AND(M80>0,C80<Resumen!$B$3),"Sí","No") | AA74: =IF(AND(L80>0,M80>0),"Sí","No") | AB74: =IF(J80="USD","Sí","No")
A75: FAC-00069 | B75: 45974 | C75: 46019 | D75: 46020 | E75: CL-014 | F75: Norte Gestión Integral S.R.L. | G75: PyME servicios recurrentes | H75: SRV-001 | I75: Abono mensual administrativo | J75: ARS | K75: 861000 | L75: 861000 | M75: 0 | N75: 1398 | O75: 0 | P75: 0 | Q75: =IF(M70<=0,"Cobrada",IF(L70>0,"Parcial",IF(C70<Resumen!$B$3,"Vencida",IF(C70<=Resumen!$B$3+15,"Por vencer","Pendiente")))) | R75: 0 | S75: =IF(M70<=0,"Sin prioridad",IF(R70>60,"Alta",IF(R70>30,"Media",IF(C70<=Resumen!$B$3+15,"Media","Baja")))) | T75: Carlos | U75: Sin acción | V75: Sin respuesta del cliente | Y75: 2025-T4 | Z75: =IF(AND(M70>0,C70<Resumen!$B$3),"Sí","No") | AA75: =IF(AND(L70>0,M70>0),"Sí","No") | AB75: =IF(J70="USD","Sí","No")
A76: FAC-00072 | B76: 45974 | C76: 46004 | D76: 46013 | E76: CL-019 | F76: Sierra Norte S.A.S. | G76: PyME servicios recurrentes | H76: SRV-002 | I76: Soporte operativo | J76: ARS | K76: 657000 | L76: 452623.92 | M76: 0 | N76: 1398 | O76: 0 | P76: 0 | Q76: =IF(M73<=0,"Cobrada",IF(L73>0,"Parcial",IF(C73<Resumen!$B$3,"Vencida",IF(C73<=Resumen!$B$3+15,"Por vencer","Pendiente")))) | R76: 0 | S76: =IF(M73<=0,"Sin prioridad",IF(R73>60,"Alta",IF(R73>30,"Media",IF(C73<=Resumen!$B$3+15,"Media","Baja")))) | T76: Carlos | U76: Reclamar saldo parcial | V76: En seguimiento administrativo | Y76: 2025-T4 | Z76: =IF(AND(M73>0,C73<Resumen!$B$3),"Sí","No") | AA76: =IF(AND(L73>0,M73>0),"Sí","No") | AB76: =IF(J73="USD","Sí","No")
A77: FAC-00088 | B77: 45974 | C77: 46019 | D77: 46029 | E77: CL-016 | F77: Patagonia Gestión S.R.L. | G77: PyME servicios recurrentes | H77: SRV-001 | I77: Abono mensual administrativo | J77: ARS | K77: 534000 | L77: 305290.35 | M77: 0 | N77: 1398 | O77: 0 | P77: 0 | Q77: =IF(M89<=0,"Cobrada",IF(L89>0,"Parcial",IF(C89<Resumen!$B$3,"Vencida",IF(C89<=Resumen!$B$3+15,"Por vencer","Pendiente")))) | R77: 0 | S77: =IF(M89<=0,"Sin prioridad",IF(R89>60,"Alta",IF(R89>30,"Media",IF(C89<=Resumen!$B$3+15,"Media","Baja")))) | T77: Matías | U77: Reclamar saldo parcial | V77: Pago prometido para próxima semana | Y77: 2025-T4 | Z77: =IF(AND(M89>0,C89<Resumen!$B$3),"Sí","No") | AA77: =IF(AND(L89>0,M89>0),"Sí","No") | AB77: =IF(J89="USD","Sí","No")
A78: FAC-00071 | B78: 45976 | C78: 45991 | E78: CL-005 | F78: Cerro Azul S.R.L. | G78: PyME servicios recurrentes | H78: SRV-002 | I78: Soporte operativo | J78: ARS | K78: 356000 | L78: 0 | M78: 0 | N78: 1398 | O78: 0 | P78: 0 | Q78: =IF(M72<=0,"Cobrada",IF(L72>0,"Parcial",IF(C72<Resumen!$B$3,"Vencida",IF(C72<=Resumen!$B$3+15,"Por vencer","Pendiente")))) | R78: 0 | S78: =IF(M72<=0,"Sin prioridad",IF(R72>60,"Alta",IF(R72>30,"Media",IF(C72<=Resumen!$B$3+15,"Media","Baja")))) | T78: Ana | U78: Reenviar factura | V78: En seguimiento administrativo | Y78: 2025-T4 | Z78: =IF(AND(M72>0,C72<Resumen!$B$3),"Sí","No") | AA78: =IF(AND(L72>0,M72>0),"Sí","No") | AB78: =IF(J72="USD","Sí","No")
A79: FAC-00083 | B79: 45979 | C79: 46009 | D79: 46012 | E79: CL-002 | F79: Andes Gestión S.A. | G79: PyME servicios recurrentes | H79: SRV-001 | I79: Abono mensual administrativo | J79: ARS | K79: 846000 | L79: 846000 | M79: 0 | N79: 1398 | O79: 0 | P79: 0 | Q79: =IF(M84<=0,"Cobrada",IF(L84>0,"Parcial",IF(C84<Resumen!$B$3,"Vencida",IF(C84<=Resumen!$B$3+15,"Por vencer","Pendiente")))) | R79: 0 | S79: =IF(M84<=0,"Sin prioridad",IF(R84>60,"Alta",IF(R84>30,"Media",IF(C84<=Resumen!$B$3+15,"Media","Baja")))) | T79: Matías | U79: Sin acción | V79: Cliente solicita reenvío de factura | Y79: 2025-T4 | Z79: =IF(AND(M84>0,C84<Resumen!$B$3),"Sí","No") | AA79: =IF(AND(L84>0,M84>0),"Sí","No") | AB79: =IF(J84="USD","Sí","No")
A80: FAC-00085 | B80: 45979 | C80: 45994 | E80: CL-003 | F80: Arco Norte S.R.L. | G80: PyME servicios recurrentes | H80: SRV-003 | I80: Consultoría de gestión | J80: USD | K80: 1150 | L80: 0 | M80: 0 | N80: 1398 | O80: 0 | P80: 0 | Q80: =IF(M86<=0,"Cobrada",IF(L86>0,"Parcial",IF(C86<Resumen!$B$3,"Vencida",IF(C86<=Resumen!$B$3+15,"Por vencer","Pendiente")))) | R80: 0 | S80: =IF(M86<=0,"Sin prioridad",IF(R86>60,"Alta",IF(R86>30,"Media",IF(C86<=Resumen!$B$3+15,"Media","Baja")))) | T80: Sofía | U80: Enviar recordatorio | V80: Cliente solicita reenvío de factura | Y80: 2025-T4 | Z80: =IF(AND(M86>0,C86<Resumen!$B$3),"Sí","No") | AA80: =IF(AND(L86>0,M86>0),"Sí","No") | AB80: =IF(J86="USD","Sí","No")
A81: FAC-00087 | B81: 45980 | C81: 46025 | D81: 46035 | E81: CL-007 | F81: Eje Comercial S.R.L. | G81: PyME servicios recurrentes | H81: SRV-004 | I81: Reporte mensual / tablero de control | J81: USD | K81: 600 | L81: 600 | M81: 0 | N81: 1398 | O81: 0 | P81: 0 | Q81: =IF(M88<=0,"Cobrada",IF(L88>0,"Parcial",IF(C88<Resumen!$B$3,"Vencida",IF(C88<=Resumen!$B$3+15,"Por vencer","Pendiente")))) | R81: 0 | S81: =IF(M88<=0,"Sin prioridad",IF(R88>60,"Alta",IF(R88>30,"Media",IF(C88<=Resumen!$B$3+15,"Media","Baja")))) | T81: Matías | U81: Sin acción | V81: Cliente solicita reenvío de factura | Y81: 2025-T4 | Z81: =IF(AND(M88>0,C88<Resumen!$B$3),"Sí","No") | AA81: =IF(AND(L88>0,M88>0),"Sí","No") | AB81: =IF(J88="USD","Sí","No")
A82: FAC-00068 | B82: 45981 | C82: 46026 | E82: CL-014 | F82: Norte Gestión Integral S.R.L. | G82: PyME servicios recurrentes | H82: SRV-002 | I82: Soporte operativo | J82: ARS | K82: 661000 | L82: 0 | M82: 0 | N82: 1398 | O82: 0 | P82: 0 | Q82: =IF(M69<=0,"Cobrada",IF(L69>0,"Parcial",IF(C69<Resumen!$B$3,"Vencida",IF(C69<=Resumen!$B$3+15,"Por vencer","Pendiente")))) | R82: 0 | S82: =IF(M69<=0,"Sin prioridad",IF(R69>60,"Alta",IF(R69>30,"Media",IF(C69<=Resumen!$B$3+15,"Media","Baja")))) | T82: Carlos | U82: Enviar recordatorio | V82: Pago prometido para próxima semana | Y82: 2025-T4 | Z82: =IF(AND(M69>0,C69<Resumen!$B$3),"Sí","No") | AA82: =IF(AND(L69>0,M69>0),"Sí","No") | AB82: =IF(J69="USD","Sí","No")
A83: FAC-00076 | B83: 45981 | C83: 45996 | D83: 46004 | E83: CL-015 | F83: Órbita Servicios S.A.S. | G83: PyME servicios recurrentes | H83: SRV-002 | I83: Soporte operativo | J83: ARS | K83: 763000 | L83: 763000 | M83: 0 | N83: 1398 | O83: 0 | P83: 0 | Q83: =IF(M77<=0,"Cobrada",IF(L77>0,"Parcial",IF(C77<Resumen!$B$3,"Vencida",IF(C77<=Resumen!$B$3+15,"Por vencer","Pendiente")))) | R83: 0 | S83: =IF(M77<=0,"Sin prioridad",IF(R77>60,"Alta",IF(R77>30,"Media",IF(C77<=Resumen!$B$3+15,"Media","Baja")))) | T83: Matías | U83: Sin acción | V83: En seguimiento administrativo | Y83: 2025-T4 | Z83: =IF(AND(M77>0,C77<Resumen!$B$3),"Sí","No") | AA83: =IF(AND(L77>0,M77>0),"Sí","No") | AB83: =IF(J77="USD","Sí","No")
A84: FAC-00077 | B84: 45982 | C84: 45997 | D84: 46019 | E84: CL-020 | F84: Tango Gestión S.R.L. | G84: PyME servicios recurrentes | H84: SRV-002 | I84: Soporte operativo | J84: USD | K84: 250 | L84: 162.75 | M84: 0 | N84: 1398 | O84: 0 | P84: 0 | Q84: =IF(M78<=0,"Cobrada",IF(L78>0,"Parcial",IF(C78<Resumen!$B$3,"Vencida",IF(C78<=Resumen!$B$3+15,"Por vencer","Pendiente")))) | R84: 0 | S84: =IF(M78<=0,"Sin prioridad",IF(R78>60,"Alta",IF(R78>30,"Media",IF(C78<=Resumen!$B$3+15,"Media","Baja")))) | T84: Ana | U84: Reclamar saldo parcial | V84: Sin respuesta del cliente | Y84: 2025-T4 | Z84: =IF(AND(M78>0,C78<Resumen!$B$3),"Sí","No") | AA84: =IF(AND(L78>0,M78>0),"Sí","No") | AB84: =IF(J78="USD","Sí","No")
A85: FAC-00078 | B85: 45982 | C85: 46027 | D85: 46052 | E85: CL-024 | F85: Zonda Gestión S.R.L. | G85: PyME servicios recurrentes | H85: SRV-004 | I85: Reporte mensual / tablero de control | J85: USD | K85: 850 | L85: 850 | M85: 0 | N85: 1398 | O85: 0 | P85: 0 | Q85: =IF(M79<=0,"Cobrada",IF(L79>0,"Parcial",IF(C79<Resumen!$B$3,"Vencida",IF(C79<=Resumen!$B$3+15,"Por vencer","Pendiente")))) | R85: 0 | S85: =IF(M79<=0,"Sin prioridad",IF(R79>60,"Alta",IF(R79>30,"Media",IF(C79<=Resumen!$B$3+15,"Media","Baja")))) | T85: Sofía | U85: Sin acción | V85: Sin respuesta del cliente | Y85: 2025-T4 | Z85: =IF(AND(M79>0,C79<Resumen!$B$3),"Sí","No") | AA85: =IF(AND(L79>0,M79>0),"Sí","No") | AB85: =IF(J79="USD","Sí","No")
A86: FAC-00081 | B86: 45982 | C86: 45997 | D86: 45994 | E86: CL-011 | F86: Impulso Gestión S.A.S. | G86: PyME servicios recurrentes | H86: SRV-001 | I86: Abono mensual administrativo | J86: ARS | K86: 356000 | L86: 356000 | M86: 0 | N86: 1398 | O86: 0 | P86: 0 | Q86: =IF(M82<=0,"Cobrada",IF(L82>0,"Parcial",IF(C82<Resumen!$B$3,"Vencida",IF(C82<=Resumen!$B$3+15,"Por vencer","Pendiente")))) | R86: 0 | S86: =IF(M82<=0,"Sin prioridad",IF(R82>60,"Alta",IF(R82>30,"Media",IF(C82<=Resumen!$B$3+15,"Media","Baja")))) | T86: Carlos | U86: Sin acción | V86: Pendiente de confirmación de pago | Y86: 2025-T4 | Z86: =IF(AND(M82>0,C82<Resumen!$B$3),"Sí","No") | AA86: =IF(AND(L82>0,M82>0),"Sí","No") | AB86: =IF(J82="USD","Sí","No")
A87: FAC-00089 | B87: 45982 | C87: 46012 | D87: 46025 | E87: CL-019 | F87: Sierra Norte S.A.S. | G87: PyME servicios recurrentes | H87: SRV-002 | I87: Soporte operativo | J87: USD | K87: 600 | L87: 600 | M87: 0 | N87: 1398 | O87: 0 | P87: 0 | Q87: =IF(M90<=0,"Cobrada",IF(L90>0,"Parcial",IF(C90<Resumen!$B$3,"Vencida",IF(C90<=Resumen!$B$3+15,"Por vencer","Pendiente")))) | R87: 0 | S87: =IF(M90<=0,"Sin prioridad",IF(R90>60,"Alta",IF(R90>30,"Media",IF(C90<=Resumen!$B$3+15,"Media","Baja")))) | T87: Carlos | U87: Sin acción | V87: Sin respuesta del cliente | Y87: 2025-T4 | Z87: =IF(AND(M90>0,C90<Resumen!$B$3),"Sí","No") | AA87: =IF(AND(L90>0,M90>0),"Sí","No") | AB87: =IF(J90="USD","Sí","No")
A88: FAC-00080 | B88: 45986 | C88: 46016 | D88: 46012 | E88: CL-009 | F88: Grupo Nexo PyME S.A. | G88: PyME servicios recurrentes | H88: SRV-001 | I88: Abono mensual administrativo | J88: ARS | K88: 371000 | L88: 371000 | M88: 0 | N88: 1398 | O88: 0 | P88: 0 | Q88: =IF(M81<=0,"Cobrada",IF(L81>0,"Parcial",IF(C81<Resumen!$B$3,"Vencida",IF(C81<=Resumen!$B$3+15,"Por vencer","Pendiente")))) | R88: 0 | S88: =IF(M81<=0,"Sin prioridad",IF(R81>60,"Alta",IF(R81>30,"Media",IF(C81<=Resumen!$B$3+15,"Media","Baja")))) | T88: Ana | U88: Sin acción | V88: Sin respuesta del cliente | Y88: 2025-T4 | Z88: =IF(AND(M81>0,C81<Resumen!$B$3),"Sí","No") | AA88: =IF(AND(L81>0,M81>0),"Sí","No") | AB88: =IF(J81="USD","Sí","No")
A89: FAC-00090 | B89: 45986 | C89: 46001 | E89: CL-017 | F89: Punto Sur S.A. | G89: PyME servicios recurrentes | H89: SRV-002 | I89: Soporte operativo | J89: ARS | K89: 587000 | L89: 0 | M89: 0 | N89: 1398 | O89: 0 | P89: 0 | Q89: =IF(M91<=0,"Cobrada",IF(L91>0,"Parcial",IF(C91<Resumen!$B$3,"Vencida",IF(C91<=Resumen!$B$3+15,"Por vencer","Pendiente")))) | R89: 0 | S89: =IF(M91<=0,"Sin prioridad",IF(R91>60,"Alta",IF(R91>30,"Media",IF(C91<=Resumen!$B$3+15,"Media","Baja")))) | T89: Sofía | U89: Enviar recordatorio | V89: Sin respuesta del cliente | Y89: 2025-T4 | Z89: =IF(AND(M91>0,C91<Resumen!$B$3),"Sí","No") | AA89: =IF(AND(L91>0,M91>0),"Sí","No") | AB89: =IF(J91="USD","Sí","No")
A90: FAC-00074 | B90: 45987 | C90: 46047 | D90: 46090 | E90: CL-006 | F90: Delta Gestión PyME S.A. | G90: PyME servicios recurrentes | H90: SRV-004 | I90: Reporte mensual / tablero de control | J90: USD | K90: 1700 | L90: 1700 | M90: 0 | N90: 1398 | O90: 0 | P90: 0 | Q90: =IF(M75<=0,"Cobrada",IF(L75>0,"Parcial",IF(C75<Resumen!$B$3,"Vencida",IF(C75<=Resumen!$B$3+15,"Por vencer","Pendiente")))) | R90: 0 | S90: =IF(M75<=0,"Sin prioridad",IF(R75>60,"Alta",IF(R75>30,"Media",IF(C75<=Resumen!$B$3+15,"Media","Baja")))) | T90: Ana | U90: Sin acción | V90: Sin respuesta del cliente | Y90: 2025-T4 | Z90: =IF(AND(M75>0,C75<Resumen!$B$3),"Sí","No") | AA90: =IF(AND(L75>0,M75>0),"Sí","No") | AB90: =IF(J75="USD","Sí","No")
A91: FAC-00086 | B91: 45987 | C91: 46032 | D91: 46034 | E91: CL-018 | F91: Río Claro Servicios S.R.L. | G91: PyME servicios recurrentes | H91: SRV-001 | I91: Abono mensual administrativo | J91: ARS | K91: 368000 | L91: 368000 | M91: 0 | N91: 1398 | O91: 0 | P91: 0 | Q91: =IF(M87<=0,"Cobrada",IF(L87>0,"Parcial",IF(C87<Resumen!$B$3,"Vencida",IF(C87<=Resumen!$B$3+15,"Por vencer","Pendiente")))) | R91: 0 | S91: =IF(M87<=0,"Sin prioridad",IF(R87>60,"Alta",IF(R87>30,"Media",IF(C87<=Resumen!$B$3+15,"Media","Baja")))) | T91: Ana | U91: Sin acción | V91: Cliente solicita reenvío de factura | Y91: 2025-T4 | Z91: =IF(AND(M87>0,C87<Resumen!$B$3),"Sí","No") | AA91: =IF(AND(L87>0,M87>0),"Sí","No") | AB91: =IF(J87="USD","Sí","No")
A92: FAC-00070 | B92: 45989 | C92: 46034 | E92: CL-022 | F92: Valle Operativo S.R.L. | G92: PyME servicios recurrentes | H92: SRV-002 | I92: Soporte operativo | J92: ARS | K92: 447000 | L92: 0 | M92: 0 | N92: 1398 | O92: 0 | P92: 0 | Q92: =IF(M71<=0,"Cobrada",IF(L71>0,"Parcial",IF(C71<Resumen!$B$3,"Vencida",IF(C71<=Resumen!$B$3+15,"Por vencer","Pendiente")))) | R92: 0 | S92: =IF(M71<=0,"Sin prioridad",IF(R71>60,"Alta",IF(R71>30,"Media",IF(C71<=Resumen!$B$3+15,"Media","Baja")))) | T92: Ana | U92: Llamar al cliente | V92: Pendiente de confirmación de pago | Y92: 2025-T4 | Z92: =IF(AND(M71>0,C71<Resumen!$B$3),"Sí","No") | AA92: =IF(AND(L71>0,M71>0),"Sí","No") | AB92: =IF(J71="USD","Sí","No")
A93: FAC-00099 | B93: 46001 | C93: 46016 | D93: 46019 | E93: CL-011 | F93: Impulso Gestión S.A.S. | G93: PyME servicios recurrentes | H93: SRV-003 | I93: Consultoría de gestión | J93: USD | K93: 1900 | L93: 1543.53 | M93: 0 | N93: 1436 | O93: 0 | P93: 0 | Q93: =IF(M100<=0,"Cobrada",IF(L100>0,"Parcial",IF(C100<Resumen!$B$3,"Vencida",IF(C100<=Resumen!$B$3+15,"Por vencer","Pendiente")))) | R93: 0 | S93: =IF(M100<=0,"Sin prioridad",IF(R100>60,"Alta",IF(R100>30,"Media",IF(C100<=Resumen!$B$3+15,"Media","Baja")))) | T93: Carlos | U93: Reclamar saldo parcial | V93: Sin respuesta del cliente | Y93: 2025-T4 | Z93: =IF(AND(M100>0,C100<Resumen!$B$3),"Sí","No") | AA93: =IF(AND(L100>0,M100>0),"Sí","No") | AB93: =IF(J100="USD","Sí","No")
A94: FAC-00100 | B94: 46002 | C94: 46062 | D94: 46078 | E94: CL-006 | F94: Delta Gestión PyME S.A. | G94: PyME servicios recurrentes | H94: SRV-003 | I94: Consultoría de gestión | J94: USD | K94: 1150 | L94: 1150 | M94: 0 | N94: 1436 | O94: 0 | P94: 0 | Q94: =IF(M101<=0,"Cobrada",IF(L101>0,"Parcial",IF(C101<Resumen!$B$3,"Vencida",IF(C101<=Resumen!$B$3+15,"Por vencer","Pendiente")))) | R94: 0 | S94: =IF(M101<=0,"Sin prioridad",IF(R101>60,"Alta",IF(R101>30,"Media",IF(C101<=Resumen!$B$3+15,"Media","Baja")))) | T94: Ana | U94: Sin acción | V94: Sin respuesta del cliente | Y94: 2025-T4 | Z94: =IF(AND(M101>0,C101<Resumen!$B$3),"Sí","No") | AA94: =IF(AND(L101>0,M101>0),"Sí","No") | AB94: =IF(J101="USD","Sí","No")
A95: FAC-00095 | B95: 46003 | C95: 46018 | D95: 46029 | E95: CL-023 | F95: Vector Administración S.A.S. | G95: PyME servicios recurrentes | H95: SRV-003 | I95: Consultoría de gestión | J95: USD | K95: 800 | L95: 800 | M95: 0 | N95: 1436 | O95: 0 | P95: 0 | Q95: =IF(M96<=0,"Cobrada",IF(L96>0,"Parcial",IF(C96<Resumen!$B$3,"Vencida",IF(C96<=Resumen!$B$3+15,"Por vencer","Pendiente")))) | R95: 0 | S95: =IF(M96<=0,"Sin prioridad",IF(R96>60,"Alta",IF(R96>30,"Media",IF(C96<=Resumen!$B$3+15,"Media","Baja")))) | T95: Ana | U95: Sin acción | V95: En seguimiento administrativo | Y95: 2025-T4 | Z95: =IF(AND(M96>0,C96<Resumen!$B$3),"Sí","No") | AA95: =IF(AND(L96>0,M96>0),"Sí","No") | AB95: =IF(J96="USD","Sí","No")
A96: FAC-00108 | B96: 46003 | C96: 46048 | E96: CL-016 | F96: Patagonia Gestión S.R.L. | G96: PyME servicios recurrentes | H96: SRV-001 | I96: Abono mensual administrativo | J96: ARS | K96: 595000 | L96: 0 | M96: 0 | N96: 1436 | O96: 0 | P96: 0 | Q96: =IF(M109<=0,"Cobrada",IF(L109>0,"Parcial",IF(C109<Resumen!$B$3,"Vencida",IF(C109<=Resumen!$B$3+15,"Por vencer","Pendiente")))) | R96: 0 | S96: =IF(M109<=0,"Sin prioridad",IF(R109>60,"Alta",IF(R109>30,"Media",IF(C109<=Resumen!$B$3+15,"Media","Baja")))) | T96: Matías | U96: Enviar recordatorio | V96: En seguimiento administrativo | Y96: 2025-T4 | Z96: =IF(AND(M109>0,C109<Resumen!$B$3),"Sí","No") | AA96: =IF(AND(L109>0,M109>0),"Sí","No") | AB96: =IF(J109="USD","Sí","No")
A97: FAC-00098 | B97: 46004 | C97: 46034 | E97: CL-009 | F97: Grupo Nexo PyME S.A. | G97: PyME servicios recurrentes | H97: SRV-001 | I97: Abono mensual administrativo | J97: ARS | K97: 578000 | L97: 0 | M97: 0 | N97: 1436 | O97: 0 | P97: 0 | Q97: =IF(M99<=0,"Cobrada",IF(L99>0,"Parcial",IF(C99<Resumen!$B$3,"Vencida",IF(C99<=Resumen!$B$3+15,"Por vencer","Pendiente")))) | R97: 0 | S97: =IF(M99<=0,"Sin prioridad",IF(R99>60,"Alta",IF(R99>30,"Media",IF(C99<=Resumen!$B$3+15,"Media","Baja")))) | T97: Ana | U97: Llamar al cliente | V97: Cliente solicita reenvío de factura | Y97: 2025-T4 | Z97: =IF(AND(M99>0,C99<Resumen!$B$3),"Sí","No") | AA97: =IF(AND(L99>0,M99>0),"Sí","No") | AB97: =IF(J99="USD","Sí","No")
A98: FAC-00104 | B98: 46004 | C98: 46019 | D98: 46019 | E98: CL-004 | F98: Base Sur Servicios S.A.S. | G98: PyME servicios recurrentes | H98: SRV-005 | I98: Servicio extraordinario puntual | J98: ARS | K98: 390000 | L98: 390000 | M98: 0 | N98: 1436 | O98: 0 | P98: 0 | Q98: =IF(M105<=0,"Cobrada",IF(L105>0,"Parcial",IF(C105<Resumen!$B$3,"Vencida",IF(C105<=Resumen!$B$3+15,"Por vencer","Pendiente")))) | R98: 0 | S98: =IF(M105<=0,"Sin prioridad",IF(R105>60,"Alta",IF(R105>30,"Media",IF(C105<=Resumen!$B$3+15,"Media","Baja")))) | T98: Ana | U98: Sin acción | V98: Sin respuesta del cliente | Y98: 2025-T4 | Z98: =IF(AND(M105>0,C105<Resumen!$B$3),"Sí","No") | AA98: =IF(AND(L105>0,M105>0),"Sí","No") | AB98: =IF(J105="USD","Sí","No")
A99: FAC-00103 | B99: 46006 | C99: 46051 | D99: 46083 | E99: CL-024 | F99: Zonda Gestión S.R.L. | G99: PyME servicios recurrentes | H99: SRV-004 | I99: Reporte mensual / tablero de control | J99: USD | K99: 550 | L99: 550 | M99: 0 | N99: 1436 | O99: 0 | P99: 0 | Q99: =IF(M104<=0,"Cobrada",IF(L104>0,"Parcial",IF(C104<Resumen!$B$3,"Vencida",IF(C104<=Resumen!$B$3+15,"Por vencer","Pendiente")))) | R99: 0 | S99: =IF(M104<=0,"Sin prioridad",IF(R104>60,"Alta",IF(R104>30,"Media",IF(C104<=Resumen!$B$3+15,"Media","Baja")))) | T99: Sofía | U99: Sin acción | Y99: 2025-T4 | Z99: =IF(AND(M104>0,C104<Resumen!$B$3),"Sí","No") | AA99: =IF(AND(L104>0,M104>0),"Sí","No") | AB99: =IF(J104="USD","Sí","No")
A100: FAC-00093 | B100: 46009 | C100: 46024 | D100: 46022 | E100: CL-011 | F100: Impulso Gestión S.A.S. | G100: PyME servicios recurrentes | H100: SRV-002 | I100: Soporte operativo | J100: ARS | K100: 285000 | L100: 285000 | M100: 0 | N100: 1436 | O100: 0 | P100: 0 | Q100: =IF(M94<=0,"Cobrada",IF(L94>0,"Parcial",IF(C94<Resumen!$B$3,"Vencida",IF(C94<=Resumen!$B$3+15,"Por vencer","Pendiente")))) | R100: 0 | S100: =IF(M94<=0,"Sin prioridad",IF(R94>60,"Alta",IF(R94>30,"Media",IF(C94<=Resumen!$B$3+15,"Media","Baja")))) | T100: Carlos | U100: Sin acción | V100: Pendiente de confirmación de pago | Y100: 2025-T4 | Z100: =IF(AND(M94>0,C94<Resumen!$B$3),"Sí","No") | AA100: =IF(AND(L94>0,M94>0),"Sí","No") | AB100: =IF(J94="USD","Sí","No")
...

Sheet Clientes
A1: id_cliente | B1: cliente | C1: tipo_cliente | D1: condicion_pago_dias | E1: perfil_pago | F1: responsable | H1: Selector y resumen por cliente
A2: {=_xlfn._xlws.SORT(_xlfn.UNIQUE(FacturasTable[id_cliente]))} | B2: =IF($A2="","",_xlfn.XLOOKUP($A2,FacturasTable[id_cliente],FacturasTable[cliente],"")) | C2: =IF($A2="","",_xlfn.XLOOKUP($A2,FacturasTable[id_cliente],FacturasTable[tipo_cliente],"")) | D2: =IF($A2="","",_xlfn.XLOOKUP($A2,FacturasTable[id_cliente],FacturasTable[fecha_vencimiento],"")-_xlfn.XLOOKUP($A2,FacturasTable[id_cliente],FacturasTable[fecha_emision],"")) | E2: =IF($A2="","",IF(AVERAGEIFS(FacturasTable[dias_atraso],FacturasTable[id_cliente],$A2,FacturasTable[dias_atraso],">0")>30,"Atraso medio",IF(AVERAGEIFS(FacturasTable[dias_atraso],FacturasTable[id_cliente],$A2,FacturasTable[dias_atraso],">0")>0,"Atraso leve","Paga en término"))) | F2: =IF($A2="","",_xlfn.XLOOKUP($A2,FacturasTable[id_cliente],FacturasTable[responsable],""))
A3: CL-002 | B3: =IF($A3="","",_xlfn.XLOOKUP($A3,FacturasTable[id_cliente],FacturasTable[cliente],"")) | C3: =IF($A3="","",_xlfn.XLOOKUP($A3,FacturasTable[id_cliente],FacturasTable[tipo_cliente],"")) | D3: =IF($A3="","",_xlfn.XLOOKUP($A3,FacturasTable[id_cliente],FacturasTable[fecha_vencimiento],"")-_xlfn.XLOOKUP($A3,FacturasTable[id_cliente],FacturasTable[fecha_emision],"")) | E3: =IF($A3="","",IF(AVERAGEIFS(FacturasTable[dias_atraso],FacturasTable[id_cliente],$A3,FacturasTable[dias_atraso],">0")>30,"Atraso medio",IF(AVERAGEIFS(FacturasTable[dias_atraso],FacturasTable[id_cliente],$A3,FacturasTable[dias_atraso],">0")>0,"Atraso leve","Paga en término"))) | F3: =IF($A3="","",_xlfn.XLOOKUP($A3,FacturasTable[id_cliente],FacturasTable[responsable],"")) | H3: Elegir cliente | I3: Punto Sur S.A.
A4: CL-003 | B4: =IF($A4="","",_xlfn.XLOOKUP($A4,FacturasTable[id_cliente],FacturasTable[cliente],"")) | C4: =IF($A4="","",_xlfn.XLOOKUP($A4,FacturasTable[id_cliente],FacturasTable[tipo_cliente],"")) | D4: =IF($A4="","",_xlfn.XLOOKUP($A4,FacturasTable[id_cliente],FacturasTable[fecha_vencimiento],"")-_xlfn.XLOOKUP($A4,FacturasTable[id_cliente],FacturasTable[fecha_emision],"")) | E4: =IF($A4="","",IF(AVERAGEIFS(FacturasTable[dias_atraso],FacturasTable[id_cliente],$A4,FacturasTable[dias_atraso],">0")>30,"Atraso medio",IF(AVERAGEIFS(FacturasTable[dias_atraso],FacturasTable[id_cliente],$A4,FacturasTable[dias_atraso],">0")>0,"Atraso leve","Paga en término"))) | F4: =IF($A4="","",_xlfn.XLOOKUP($A4,FacturasTable[id_cliente],FacturasTable[responsable],""))
A5: CL-004 | B5: =IF($A5="","",_xlfn.XLOOKUP($A5,FacturasTable[id_cliente],FacturasTable[cliente],"")) | C5: =IF($A5="","",_xlfn.XLOOKUP($A5,FacturasTable[id_cliente],FacturasTable[tipo_cliente],"")) | D5: =IF($A5="","",_xlfn.XLOOKUP($A5,FacturasTable[id_cliente],FacturasTable[fecha_vencimiento],"")-_xlfn.XLOOKUP($A5,FacturasTable[id_cliente],FacturasTable[fecha_emision],"")) | E5: =IF($A5="","",IF(AVERAGEIFS(FacturasTable[dias_atraso],FacturasTable[id_cliente],$A5,FacturasTable[dias_atraso],">0")>30,"Atraso medio",IF(AVERAGEIFS(FacturasTable[dias_atraso],FacturasTable[id_cliente],$A5,FacturasTable[dias_atraso],">0")>0,"Atraso leve","Paga en término"))) | F5: =IF($A5="","",_xlfn.XLOOKUP($A5,FacturasTable[id_cliente],FacturasTable[responsable],"")) | H5: id_cliente | I5: =IFERROR(_xlfn.XLOOKUP($I$3,$B$2:$B$999,$A$2:$A$999,""),"")
A6: CL-005 | B6: =IF($A6="","",_xlfn.XLOOKUP($A6,FacturasTable[id_cliente],FacturasTable[cliente],"")) | C6: =IF($A6="","",_xlfn.XLOOKUP($A6,FacturasTable[id_cliente],FacturasTable[tipo_cliente],"")) | D6: =IF($A6="","",_xlfn.XLOOKUP($A6,FacturasTable[id_cliente],FacturasTable[fecha_vencimiento],"")-_xlfn.XLOOKUP($A6,FacturasTable[id_cliente],FacturasTable[fecha_emision],"")) | E6: =IF($A6="","",IF(AVERAGEIFS(FacturasTable[dias_atraso],FacturasTable[id_cliente],$A6,FacturasTable[dias_atraso],">0")>30,"Atraso medio",IF(AVERAGEIFS(FacturasTable[dias_atraso],FacturasTable[id_cliente],$A6,FacturasTable[dias_atraso],">0")>0,"Atraso leve","Paga en término"))) | F6: =IF($A6="","",_xlfn.XLOOKUP($A6,FacturasTable[id_cliente],FacturasTable[responsable],"")) | H6: tipo_cliente | I6: =IF($I$5="","",_xlfn.XLOOKUP($I$5,$A$2:$A$999,$C$2:$C$999,""))
A7: CL-006 | B7: =IF($A7="","",_xlfn.XLOOKUP($A7,FacturasTable[id_cliente],FacturasTable[cliente],"")) | C7: =IF($A7="","",_xlfn.XLOOKUP($A7,FacturasTable[id_cliente],FacturasTable[tipo_cliente],"")) | D7: =IF($A7="","",_xlfn.XLOOKUP($A7,FacturasTable[id_cliente],FacturasTable[fecha_vencimiento],"")-_xlfn.XLOOKUP($A7,FacturasTable[id_cliente],FacturasTable[fecha_emision],"")) | E7: =IF($A7="","",IF(AVERAGEIFS(FacturasTable[dias_atraso],FacturasTable[id_cliente],$A7,FacturasTable[dias_atraso],">0")>30,"Atraso medio",IF(AVERAGEIFS(FacturasTable[dias_atraso],FacturasTable[id_cliente],$A7,FacturasTable[dias_atraso],">0")>0,"Atraso leve","Paga en término"))) | F7: =IF($A7="","",_xlfn.XLOOKUP($A7,FacturasTable[id_cliente],FacturasTable[responsable],"")) | H7: responsable | I7: =IF($I$5="","",_xlfn.XLOOKUP($I$5,$A$2:$A$999,$F$2:$F$999,""))
A8: CL-007 | B8: =IF($A8="","",_xlfn.XLOOKUP($A8,FacturasTable[id_cliente],FacturasTable[cliente],"")) | C8: =IF($A8="","",_xlfn.XLOOKUP($A8,FacturasTable[id_cliente],FacturasTable[tipo_cliente],"")) | D8: =IF($A8="","",_xlfn.XLOOKUP($A8,FacturasTable[id_cliente],FacturasTable[fecha_vencimiento],"")-_xlfn.XLOOKUP($A8,FacturasTable[id_cliente],FacturasTable[fecha_emision],"")) | E8: =IF($A8="","",IF(AVERAGEIFS(FacturasTable[dias_atraso],FacturasTable[id_cliente],$A8,FacturasTable[dias_atraso],">0")>30,"Atraso medio",IF(AVERAGEIFS(FacturasTable[dias_atraso],FacturasTable[id_cliente],$A8,FacturasTable[dias_atraso],">0")>0,"Atraso leve","Paga en término"))) | F8: =IF($A8="","",_xlfn.XLOOKUP($A8,FacturasTable[id_cliente],FacturasTable[responsable],"")) | H8: condición_pago_días | I8: =IF($I$5="","",_xlfn.XLOOKUP($I$5,$A$2:$A$999,$D$2:$D$999,""))
A9: CL-008 | B9: =IF($A9="","",_xlfn.XLOOKUP($A9,FacturasTable[id_cliente],FacturasTable[cliente],"")) | C9: =IF($A9="","",_xlfn.XLOOKUP($A9,FacturasTable[id_cliente],FacturasTable[tipo_cliente],"")) | D9: =IF($A9="","",_xlfn.XLOOKUP($A9,FacturasTable[id_cliente],FacturasTable[fecha_vencimiento],"")-_xlfn.XLOOKUP($A9,FacturasTable[id_cliente],FacturasTable[fecha_emision],"")) | E9: =IF($A9="","",IF(AVERAGEIFS(FacturasTable[dias_atraso],FacturasTable[id_cliente],$A9,FacturasTable[dias_atraso],">0")>30,"Atraso medio",IF(AVERAGEIFS(FacturasTable[dias_atraso],FacturasTable[id_cliente],$A9,FacturasTable[dias_atraso],">0")>0,"Atraso leve","Paga en término"))) | F9: =IF($A9="","",_xlfn.XLOOKUP($A9,FacturasTable[id_cliente],FacturasTable[responsable],""))
A10: CL-009 | B10: =IF($A10="","",_xlfn.XLOOKUP($A10,FacturasTable[id_cliente],FacturasTable[cliente],"")) | C10: =IF($A10="","",_xlfn.XLOOKUP($A10,FacturasTable[id_cliente],FacturasTable[tipo_cliente],"")) | D10: =IF($A10="","",_xlfn.XLOOKUP($A10,FacturasTable[id_cliente],FacturasTable[fecha_vencimiento],"")-_xlfn.XLOOKUP($A10,FacturasTable[id_cliente],FacturasTable[fecha_emision],"")) | E10: =IF($A10="","",IF(AVERAGEIFS(FacturasTable[dias_atraso],FacturasTable[id_cliente],$A10,FacturasTable[dias_atraso],">0")>30,"Atraso medio",IF(AVERAGEIFS(FacturasTable[dias_atraso],FacturasTable[id_cliente],$A10,FacturasTable[dias_atraso],">0")>0,"Atraso leve","Paga en término"))) | F10: =IF($A10="","",_xlfn.XLOOKUP($A10,FacturasTable[id_cliente],FacturasTable[responsable],"")) | H10: total_facturado_eq_ars | I10: =IF($I$5="","",SUMIFS(FacturasTable[importe_equivalente_ars],FacturasTable[id_cliente],$I$5))
A11: CL-010 | B11: =IF($A11="","",_xlfn.XLOOKUP($A11,FacturasTable[id_cliente],FacturasTable[cliente],"")) | C11: =IF($A11="","",_xlfn.XLOOKUP($A11,FacturasTable[id_cliente],FacturasTable[tipo_cliente],"")) | D11: =IF($A11="","",_xlfn.XLOOKUP($A11,FacturasTable[id_cliente],FacturasTable[fecha_vencimiento],"")-_xlfn.XLOOKUP($A11,FacturasTable[id_cliente],FacturasTable[fecha_emision],"")) | E11: =IF($A11="","",IF(AVERAGEIFS(FacturasTable[dias_atraso],FacturasTable[id_cliente],$A11,FacturasTable[dias_atraso],">0")>30,"Atraso medio",IF(AVERAGEIFS(FacturasTable[dias_atraso],FacturasTable[id_cliente],$A11,FacturasTable[dias_atraso],">0")>0,"Atraso leve","Paga en término"))) | F11: =IF($A11="","",_xlfn.XLOOKUP($A11,FacturasTable[id_cliente],FacturasTable[responsable],"")) | H11: total_cobrado_eq_ars | I11: =IF($I$5="","",$I$10-$I$12)
A12: CL-011 | B12: =IF($A12="","",_xlfn.XLOOKUP($A12,FacturasTable[id_cliente],FacturasTable[cliente],"")) | C12: =IF($A12="","",_xlfn.XLOOKUP($A12,FacturasTable[id_cliente],FacturasTable[tipo_cliente],"")) | D12: =IF($A12="","",_xlfn.XLOOKUP($A12,FacturasTable[id_cliente],FacturasTable[fecha_vencimiento],"")-_xlfn.XLOOKUP($A12,FacturasTable[id_cliente],FacturasTable[fecha_emision],"")) | E12: =IF($A12="","",IF(AVERAGEIFS(FacturasTable[dias_atraso],FacturasTable[id_cliente],$A12,FacturasTable[dias_atraso],">0")>30,"Atraso medio",IF(AVERAGEIFS(FacturasTable[dias_atraso],FacturasTable[id_cliente],$A12,FacturasTable[dias_atraso],">0")>0,"Atraso leve","Paga en término"))) | F12: =IF($A12="","",_xlfn.XLOOKUP($A12,FacturasTable[id_cliente],FacturasTable[responsable],"")) | H12: saldo_pendiente_eq_ars | I12: =IF($I$5="","",SUMIFS(FacturasTable[saldo_equivalente_ars],FacturasTable[id_cliente],$I$5))
A13: CL-012 | B13: =IF($A13="","",_xlfn.XLOOKUP($A13,FacturasTable[id_cliente],FacturasTable[cliente],"")) | C13: =IF($A13="","",_xlfn.XLOOKUP($A13,FacturasTable[id_cliente],FacturasTable[tipo_cliente],"")) | D13: =IF($A13="","",_xlfn.XLOOKUP($A13,FacturasTable[id_cliente],FacturasTable[fecha_vencimiento],"")-_xlfn.XLOOKUP($A13,FacturasTable[id_cliente],FacturasTable[fecha_emision],"")) | E13: =IF($A13="","",IF(AVERAGEIFS(FacturasTable[dias_atraso],FacturasTable[id_cliente],$A13,FacturasTable[dias_atraso],">0")>30,"Atraso medio",IF(AVERAGEIFS(FacturasTable[dias_atraso],FacturasTable[id_cliente],$A13,FacturasTable[dias_atraso],">0")>0,"Atraso leve","Paga en término"))) | F13: =IF($A13="","",_xlfn.XLOOKUP($A13,FacturasTable[id_cliente],FacturasTable[responsable],"")) | H13: saldo_pendiente_usd | I13: =IF($I$5="","",SUMIFS(FacturasTable[saldo_pendiente],FacturasTable[id_cliente],$I$5,FacturasTable[moneda],"USD"))
A14: CL-013 | B14: =IF($A14="","",_xlfn.XLOOKUP($A14,FacturasTable[id_cliente],FacturasTable[cliente],"")) | C14: =IF($A14="","",_xlfn.XLOOKUP($A14,FacturasTable[id_cliente],FacturasTable[tipo_cliente],"")) | D14: =IF($A14="","",_xlfn.XLOOKUP($A14,FacturasTable[id_cliente],FacturasTable[fecha_vencimiento],"")-_xlfn.XLOOKUP($A14,FacturasTable[id_cliente],FacturasTable[fecha_emision],"")) | E14: =IF($A14="","",IF(AVERAGEIFS(FacturasTable[dias_atraso],FacturasTable[id_cliente],$A14,FacturasTable[dias_atraso],">0")>30,"Atraso medio",IF(AVERAGEIFS(FacturasTable[dias_atraso],FacturasTable[id_cliente],$A14,FacturasTable[dias_atraso],">0")>0,"Atraso leve","Paga en término"))) | F14: =IF($A14="","",_xlfn.XLOOKUP($A14,FacturasTable[id_cliente],FacturasTable[responsable],"")) | H14: facturas_abiertas | I14: =IF($I$5="","",COUNTIFS(FacturasTable[id_cliente],$I$5,FacturasTable[saldo_pendiente],">0"))
A15: CL-014 | B15: =IF($A15="","",_xlfn.XLOOKUP($A15,FacturasTable[id_cliente],FacturasTable[cliente],"")) | C15: =IF($A15="","",_xlfn.XLOOKUP($A15,FacturasTable[id_cliente],FacturasTable[tipo_cliente],"")) | D15: =IF($A15="","",_xlfn.XLOOKUP($A15,FacturasTable[id_cliente],FacturasTable[fecha_vencimiento],"")-_xlfn.XLOOKUP($A15,FacturasTable[id_cliente],FacturasTable[fecha_emision],"")) | E15: =IF($A15="","",IF(AVERAGEIFS(FacturasTable[dias_atraso],FacturasTable[id_cliente],$A15,FacturasTable[dias_atraso],">0")>30,"Atraso medio",IF(AVERAGEIFS(FacturasTable[dias_atraso],FacturasTable[id_cliente],$A15,FacturasTable[dias_atraso],">0")>0,"Atraso leve","Paga en término"))) | F15: =IF($A15="","",_xlfn.XLOOKUP($A15,FacturasTable[id_cliente],FacturasTable[responsable],"")) | H15: facturas_vencidas | I15: =IF($I$5="","",COUNTIFS(FacturasTable[id_cliente],$I$5,FacturasTable[vencida_si_no],"Sí"))
A16: CL-015 | B16: =IF($A16="","",_xlfn.XLOOKUP($A16,FacturasTable[id_cliente],FacturasTable[cliente],"")) | C16: =IF($A16="","",_xlfn.XLOOKUP($A16,FacturasTable[id_cliente],FacturasTable[tipo_cliente],"")) | D16: =IF($A16="","",_xlfn.XLOOKUP($A16,FacturasTable[id_cliente],FacturasTable[fecha_vencimiento],"")-_xlfn.XLOOKUP($A16,FacturasTable[id_cliente],FacturasTable[fecha_emision],"")) | E16: =IF($A16="","",IF(AVERAGEIFS(FacturasTable[dias_atraso],FacturasTable[id_cliente],$A16,FacturasTable[dias_atraso],">0")>30,"Atraso medio",IF(AVERAGEIFS(FacturasTable[dias_atraso],FacturasTable[id_cliente],$A16,FacturasTable[dias_atraso],">0")>0,"Atraso leve","Paga en término"))) | F16: =IF($A16="","",_xlfn.XLOOKUP($A16,FacturasTable[id_cliente],FacturasTable[responsable],"")) | H16: mora_promedio_días | I16: =IFERROR(AVERAGEIFS(FacturasTable[dias_atraso],FacturasTable[id_cliente],$I$5,FacturasTable[dias_atraso],">0"),0)
A17: CL-016 | B17: =IF($A17="","",_xlfn.XLOOKUP($A17,FacturasTable[id_cliente],FacturasTable[cliente],"")) | C17: =IF($A17="","",_xlfn.XLOOKUP($A17,FacturasTable[id_cliente],FacturasTable[tipo_cliente],"")) | D17: =IF($A17="","",_xlfn.XLOOKUP($A17,FacturasTable[id_cliente],FacturasTable[fecha_vencimiento],"")-_xlfn.XLOOKUP($A17,FacturasTable[id_cliente],FacturasTable[fecha_emision],"")) | E17: =IF($A17="","",IF(AVERAGEIFS(FacturasTable[dias_atraso],FacturasTable[id_cliente],$A17,FacturasTable[dias_atraso],">0")>30,"Atraso medio",IF(AVERAGEIFS(FacturasTable[dias_atraso],FacturasTable[id_cliente],$A17,FacturasTable[dias_atraso],">0")>0,"Atraso leve","Paga en término"))) | F17: =IF($A17="","",_xlfn.XLOOKUP($A17,FacturasTable[id_cliente],FacturasTable[responsable],"")) | H17: última_factura | I17: =IF($I$5="","",_xlfn.MAXIFS(FacturasTable[fecha_emision],FacturasTable[id_cliente],$I$5))
A18: CL-017 | B18: =IF($A18="","",_xlfn.XLOOKUP($A18,FacturasTable[id_cliente],FacturasTable[cliente],"")) | C18: =IF($A18="","",_xlfn.XLOOKUP($A18,FacturasTable[id_cliente],FacturasTable[tipo_cliente],"")) | D18: =IF($A18="","",_xlfn.XLOOKUP($A18,FacturasTable[id_cliente],FacturasTable[fecha_vencimiento],"")-_xlfn.XLOOKUP($A18,FacturasTable[id_cliente],FacturasTable[fecha_emision],"")) | E18: =IF($A18="","",IF(AVERAGEIFS(FacturasTable[dias_atraso],FacturasTable[id_cliente],$A18,FacturasTable[dias_atraso],">0")>30,"Atraso medio",IF(AVERAGEIFS(FacturasTable[dias_atraso],FacturasTable[id_cliente],$A18,FacturasTable[dias_atraso],">0")>0,"Atraso leve","Paga en término"))) | F18: =IF($A18="","",_xlfn.XLOOKUP($A18,FacturasTable[id_cliente],FacturasTable[responsable],"")) | H18: próxima_acción | I18: Reclamar saldo parcial
A19: CL-018 | B19: =IF($A19="","",_xlfn.XLOOKUP($A19,FacturasTable[id_cliente],FacturasTable[cliente],"")) | C19: =IF($A19="","",_xlfn.XLOOKUP($A19,FacturasTable[id_cliente],FacturasTable[tipo_cliente],"")) | D19: =IF($A19="","",_xlfn.XLOOKUP($A19,FacturasTable[id_cliente],FacturasTable[fecha_vencimiento],"")-_xlfn.XLOOKUP($A19,FacturasTable[id_cliente],FacturasTable[fecha_emision],"")) | E19: =IF($A19="","",IF(AVERAGEIFS(FacturasTable[dias_atraso],FacturasTable[id_cliente],$A19,FacturasTable[dias_atraso],">0")>30,"Atraso medio",IF(AVERAGEIFS(FacturasTable[dias_atraso],FacturasTable[id_cliente],$A19,FacturasTable[dias_atraso],">0")>0,"Atraso leve","Paga en término"))) | F19: =IF($A19="","",_xlfn.XLOOKUP($A19,FacturasTable[id_cliente],FacturasTable[responsable],"")) | H19: vencimiento_más_antiguo_pendiente | I19: =IFERROR(_xlfn.MINIFS(Facturas!$C$2:$C$237,Facturas!$E$2:$E$237,$I$5,Facturas!$M$2:$M$237,">0"),"")
A20: CL-019 | B20: =IF($A20="","",_xlfn.XLOOKUP($A20,FacturasTable[id_cliente],FacturasTable[cliente],"")) | C20: =IF($A20="","",_xlfn.XLOOKUP($A20,FacturasTable[id_cliente],FacturasTable[tipo_cliente],"")) | D20: =IF($A20="","",_xlfn.XLOOKUP($A20,FacturasTable[id_cliente],FacturasTable[fecha_vencimiento],"")-_xlfn.XLOOKUP($A20,FacturasTable[id_cliente],FacturasTable[fecha_emision],"")) | E20: =IF($A20="","",IF(AVERAGEIFS(FacturasTable[dias_atraso],FacturasTable[id_cliente],$A20,FacturasTable[dias_atraso],">0")>30,"Atraso medio",IF(AVERAGEIFS(FacturasTable[dias_atraso],FacturasTable[id_cliente],$A20,FacturasTable[dias_atraso],">0")>0,"Atraso leve","Paga en término"))) | F20: =IF($A20="","",_xlfn.XLOOKUP($A20,FacturasTable[id_cliente],FacturasTable[responsable],"")) | H20: tiene_deuda | I20: =IF($I$12>0,"Sí","No")
A21: CL-020 | B21: =IF($A21="","",_xlfn.XLOOKUP($A21,FacturasTable[id_cliente],FacturasTable[cliente],"")) | C21: =IF($A21="","",_xlfn.XLOOKUP($A21,FacturasTable[id_cliente],FacturasTable[tipo_cliente],"")) | D21: =IF($A21="","",_xlfn.XLOOKUP($A21,FacturasTable[id_cliente],FacturasTable[fecha_vencimiento],"")-_xlfn.XLOOKUP($A21,FacturasTable[id_cliente],FacturasTable[fecha_emision],"")) | E21: =IF($A21="","",IF(AVERAGEIFS(FacturasTable[dias_atraso],FacturasTable[id_cliente],$A21,FacturasTable[dias_atraso],">0")>30,"Atraso medio",IF(AVERAGEIFS(FacturasTable[dias_atraso],FacturasTable[id_cliente],$A21,FacturasTable[dias_atraso],">0")>0,"Atraso leve","Paga en término"))) | F21: =IF($A21="","",_xlfn.XLOOKUP($A21,FacturasTable[id_cliente],FacturasTable[responsable],""))
A22: CL-021 | B22: =IF($A22="","",_xlfn.XLOOKUP($A22,FacturasTable[id_cliente],FacturasTable[cliente],"")) | C22: =IF($A22="","",_xlfn.XLOOKUP($A22,FacturasTable[id_cliente],FacturasTable[tipo_cliente],"")) | D22: =IF($A22="","",_xlfn.XLOOKUP($A22,FacturasTable[id_cliente],FacturasTable[fecha_vencimiento],"")-_xlfn.XLOOKUP($A22,FacturasTable[id_cliente],FacturasTable[fecha_emision],"")) | E22: =IF($A22="","",IF(AVERAGEIFS(FacturasTable[dias_atraso],FacturasTable[id_cliente],$A22,FacturasTable[dias_atraso],">0")>30,"Atraso medio",IF(AVERAGEIFS(FacturasTable[dias_atraso],FacturasTable[id_cliente],$A22,FacturasTable[dias_atraso],">0")>0,"Atraso leve","Paga en término"))) | F22: =IF($A22="","",_xlfn.XLOOKUP($A22,FacturasTable[id_cliente],FacturasTable[responsable],""))
A23: CL-022 | B23: =IF($A23="","",_xlfn.XLOOKUP($A23,FacturasTable[id_cliente],FacturasTable[cliente],"")) | C23: =IF($A23="","",_xlfn.XLOOKUP($A23,FacturasTable[id_cliente],FacturasTable[tipo_cliente],"")) | D23: =IF($A23="","",_xlfn.XLOOKUP($A23,FacturasTable[id_cliente],FacturasTable[fecha_vencimiento],"")-_xlfn.XLOOKUP($A23,FacturasTable[id_cliente],FacturasTable[fecha_emision],"")) | E23: =IF($A23="","",IF(AVERAGEIFS(FacturasTable[dias_atraso],FacturasTable[id_cliente],$A23,FacturasTable[dias_atraso],">0")>30,"Atraso medio",IF(AVERAGEIFS(FacturasTable[dias_atraso],FacturasTable[id_cliente],$A23,FacturasTable[dias_atraso],">0")>0,"Atraso leve","Paga en término"))) | F23: =IF($A23="","",_xlfn.XLOOKUP($A23,FacturasTable[id_cliente],FacturasTable[responsable],""))
A24: CL-023 | B24: =IF($A24="","",_xlfn.XLOOKUP($A24,FacturasTable[id_cliente],FacturasTable[cliente],"")) | C24: =IF($A24="","",_xlfn.XLOOKUP($A24,FacturasTable[id_cliente],FacturasTable[tipo_cliente],"")) | D24: =IF($A24="","",_xlfn.XLOOKUP($A24,FacturasTable[id_cliente],FacturasTable[fecha_vencimiento],"")-_xlfn.XLOOKUP($A24,FacturasTable[id_cliente],FacturasTable[fecha_emision],"")) | E24: =IF($A24="","",IF(AVERAGEIFS(FacturasTable[dias_atraso],FacturasTable[id_cliente],$A24,FacturasTable[dias_atraso],">0")>30,"Atraso medio",IF(AVERAGEIFS(FacturasTable[dias_atraso],FacturasTable[id_cliente],$A24,FacturasTable[dias_atraso],">0")>0,"Atraso leve","Paga en término"))) | F24: =IF($A24="","",_xlfn.XLOOKUP($A24,FacturasTable[id_cliente],FacturasTable[responsable],""))
A25: CL-024 | B25: =IF($A25="","",_xlfn.XLOOKUP($A25,FacturasTable[id_cliente],FacturasTable[cliente],"")) | C25: =IF($A25="","",_xlfn.XLOOKUP($A25,FacturasTable[id_cliente],FacturasTable[tipo_cliente],"")) | D25: =IF($A25="","",_xlfn.XLOOKUP($A25,FacturasTable[id_cliente],FacturasTable[fecha_vencimiento],"")-_xlfn.XLOOKUP($A25,FacturasTable[id_cliente],FacturasTable[fecha_emision],"")) | E25: =IF($A25="","",IF(AVERAGEIFS(FacturasTable[dias_atraso],FacturasTable[id_cliente],$A25,FacturasTable[dias_atraso],">0")>30,"Atraso medio",IF(AVERAGEIFS(FacturasTable[dias_atraso],FacturasTable[id_cliente],$A25,FacturasTable[dias_atraso],">0")>0,"Atraso leve","Paga en término"))) | F25: =IF($A25="","",_xlfn.XLOOKUP($A25,FacturasTable[id_cliente],FacturasTable[responsable],""))
B26: =IF($A26="","",_xlfn.XLOOKUP($A26,FacturasTable[id_cliente],FacturasTable[cliente],"")) | C26: =IF($A26="","",_xlfn.XLOOKUP($A26,FacturasTable[id_cliente],FacturasTable[tipo_cliente],"")) | D26: =IF($A26="","",_xlfn.XLOOKUP($A26,FacturasTable[id_cliente],FacturasTable[fecha_vencimiento],"")-_xlfn.XLOOKUP($A26,FacturasTable[id_cliente],FacturasTable[fecha_emision],"")) | E26: =IF($A26="","",IF(AVERAGEIFS(FacturasTable[dias_atraso],FacturasTable[id_cliente],$A26,FacturasTable[dias_atraso],">0")>30,"Atraso medio",IF(AVERAGEIFS(FacturasTable[dias_atraso],FacturasTable[id_cliente],$A26,FacturasTable[dias_atraso],">0")>0,"Atraso leve","Paga en término"))) | F26: =IF($A26="","",_xlfn.XLOOKUP($A26,FacturasTable[id_cliente],FacturasTable[responsable],""))
B27: =IF($A27="","",_xlfn.XLOOKUP($A27,FacturasTable[id_cliente],FacturasTable[cliente],"")) | C27: =IF($A27="","",_xlfn.XLOOKUP($A27,FacturasTable[id_cliente],FacturasTable[tipo_cliente],"")) | D27: =IF($A27="","",_xlfn.XLOOKUP($A27,FacturasTable[id_cliente],FacturasTable[fecha_vencimiento],"")-_xlfn.XLOOKUP($A27,FacturasTable[id_cliente],FacturasTable[fecha_emision],"")) | E27: =IF($A27="","",IF(AVERAGEIFS(FacturasTable[dias_atraso],FacturasTable[id_cliente],$A27,FacturasTable[dias_atraso],">0")>30,"Atraso medio",IF(AVERAGEIFS(FacturasTable[dias_atraso],FacturasTable[id_cliente],$A27,FacturasTable[dias_atraso],">0")>0,"Atraso leve","Paga en término"))) | F27: =IF($A27="","",_xlfn.XLOOKUP($A27,FacturasTable[id_cliente],FacturasTable[responsable],""))
B28: =IF($A28="","",_xlfn.XLOOKUP($A28,FacturasTable[id_cliente],FacturasTable[cliente],"")) | C28: =IF($A28="","",_xlfn.XLOOKUP($A28,FacturasTable[id_cliente],FacturasTable[tipo_cliente],"")) | D28: =IF($A28="","",_xlfn.XLOOKUP($A28,FacturasTable[id_cliente],FacturasTable[fecha_vencimiento],"")-_xlfn.XLOOKUP($A28,FacturasTable[id_cliente],FacturasTable[fecha_emision],"")) | E28: =IF($A28="","",IF(AVERAGEIFS(FacturasTable[dias_atraso],FacturasTable[id_cliente],$A28,FacturasTable[dias_atraso],">0")>30,"Atraso medio",IF(AVERAGEIFS(FacturasTable[dias_atraso],FacturasTable[id_cliente],$A28,FacturasTable[dias_atraso],">0")>0,"Atraso leve","Paga en término"))) | F28: =IF($A28="","",_xlfn.XLOOKUP($A28,FacturasTable[id_cliente],FacturasTable[responsable],""))

Sheet Servicios
A1: id_servicio | B1: tipo_servicio | C1: moneda_principal | D1: facturas | E1: total_facturado_eq_ars | F1: saldo_pendiente_eq_ars | G1: facturado_usd_original | H1: observación
A2: {=_xlfn._xlws.SORT(_xlfn.UNIQUE(FacturasTable[id_servicio]))} | B2: =IF($A2="","",_xlfn.XLOOKUP($A2,FacturasTable[id_servicio],FacturasTable[tipo_servicio],"")) | C2: =IF($A2="","",IF(COUNTIFS(FacturasTable[id_servicio],$A2,FacturasTable[moneda],"USD")>=COUNTIFS(FacturasTable[id_servicio],$A2,FacturasTable[moneda],"ARS"),"USD","ARS")) | D2: =IF($A2="","",COUNTIFS(FacturasTable[id_servicio],$A2)) | E2: =IF($A2="","",SUMIFS(FacturasTable[importe_equivalente_ars],FacturasTable[id_servicio],$A2)) | F2: =IF($A2="","",SUMIFS(FacturasTable[saldo_equivalente_ars],FacturasTable[id_servicio],$A2)) | G2: =IF($A2="","",SUMIFS(FacturasTable[importe_facturado],FacturasTable[id_servicio],$A2,FacturasTable[moneda],"USD")) | H2: =IF($A2="","",IF($F2>0,"Con deuda pendiente","Sin deuda pendiente"))
A3: SRV-002 | B3: =IF($A3="","",_xlfn.XLOOKUP($A3,FacturasTable[id_servicio],FacturasTable[tipo_servicio],"")) | C3: =IF($A3="","",IF(COUNTIFS(FacturasTable[id_servicio],$A3,FacturasTable[moneda],"USD")>=COUNTIFS(FacturasTable[id_servicio],$A3,FacturasTable[moneda],"ARS"),"USD","ARS")) | D3: =IF($A3="","",COUNTIFS(FacturasTable[id_servicio],$A3)) | E3: =IF($A3="","",SUMIFS(FacturasTable[importe_equivalente_ars],FacturasTable[id_servicio],$A3)) | F3: =IF($A3="","",SUMIFS(FacturasTable[saldo_equivalente_ars],FacturasTable[id_servicio],$A3)) | G3: =IF($A3="","",SUMIFS(FacturasTable[importe_facturado],FacturasTable[id_servicio],$A3,FacturasTable[moneda],"USD")) | H3: =IF($A3="","",IF($F3>0,"Con deuda pendiente","Sin deuda pendiente"))
A4: SRV-003 | B4: =IF($A4="","",_xlfn.XLOOKUP($A4,FacturasTable[id_servicio],FacturasTable[tipo_servicio],"")) | C4: =IF($A4="","",IF(COUNTIFS(FacturasTable[id_servicio],$A4,FacturasTable[moneda],"USD")>=COUNTIFS(FacturasTable[id_servicio],$A4,FacturasTable[moneda],"ARS"),"USD","ARS")) | D4: =IF($A4="","",COUNTIFS(FacturasTable[id_servicio],$A4)) | E4: =IF($A4="","",SUMIFS(FacturasTable[importe_equivalente_ars],FacturasTable[id_servicio],$A4)) | F4: =IF($A4="","",SUMIFS(FacturasTable[saldo_equivalente_ars],FacturasTable[id_servicio],$A4)) | G4: =IF($A4="","",SUMIFS(FacturasTable[importe_facturado],FacturasTable[id_servicio],$A4,FacturasTable[moneda],"USD")) | H4: =IF($A4="","",IF($F4>0,"Con deuda pendiente","Sin deuda pendiente"))
A5: SRV-004 | B5: =IF($A5="","",_xlfn.XLOOKUP($A5,FacturasTable[id_servicio],FacturasTable[tipo_servicio],"")) | C5: =IF($A5="","",IF(COUNTIFS(FacturasTable[id_servicio],$A5,FacturasTable[moneda],"USD")>=COUNTIFS(FacturasTable[id_servicio],$A5,FacturasTable[moneda],"ARS"),"USD","ARS")) | D5: =IF($A5="","",COUNTIFS(FacturasTable[id_servicio],$A5)) | E5: =IF($A5="","",SUMIFS(FacturasTable[importe_equivalente_ars],FacturasTable[id_servicio],$A5)) | F5: =IF($A5="","",SUMIFS(FacturasTable[saldo_equivalente_ars],FacturasTable[id_servicio],$A5)) | G5: =IF($A5="","",SUMIFS(FacturasTable[importe_facturado],FacturasTable[id_servicio],$A5,FacturasTable[moneda],"USD")) | H5: =IF($A5="","",IF($F5>0,"Con deuda pendiente","Sin deuda pendiente"))
A6: SRV-005 | B6: =IF($A6="","",_xlfn.XLOOKUP($A6,FacturasTable[id_servicio],FacturasTable[tipo_servicio],"")) | C6: =IF($A6="","",IF(COUNTIFS(FacturasTable[id_servicio],$A6,FacturasTable[moneda],"USD")>=COUNTIFS(FacturasTable[id_servicio],$A6,FacturasTable[moneda],"ARS"),"USD","ARS")) | D6: =IF($A6="","",COUNTIFS(FacturasTable[id_servicio],$A6)) | E6: =IF($A6="","",SUMIFS(FacturasTable[importe_equivalente_ars],FacturasTable[id_servicio],$A6)) | F6: =IF($A6="","",SUMIFS(FacturasTable[saldo_equivalente_ars],FacturasTable[id_servicio],$A6)) | G6: =IF($A6="","",SUMIFS(FacturasTable[importe_facturado],FacturasTable[id_servicio],$A6,FacturasTable[moneda],"USD")) | H6: =IF($A6="","",IF($F6>0,"Con deuda pendiente","Sin deuda pendiente"))
B7: =IF($A7="","",_xlfn.XLOOKUP($A7,FacturasTable[id_servicio],FacturasTable[tipo_servicio],"")) | C7: =IF($A7="","",IF(COUNTIFS(FacturasTable[id_servicio],$A7,FacturasTable[moneda],"USD")>=COUNTIFS(FacturasTable[id_servicio],$A7,FacturasTable[moneda],"ARS"),"USD","ARS")) | D7: =IF($A7="","",COUNTIFS(FacturasTable[id_servicio],$A7)) | E7: =IF($A7="","",SUMIFS(FacturasTable[importe_equivalente_ars],FacturasTable[id_servicio],$A7)) | F7: =IF($A7="","",SUMIFS(FacturasTable[saldo_equivalente_ars],FacturasTable[id_servicio],$A7)) | G7: =IF($A7="","",SUMIFS(FacturasTable[importe_facturado],FacturasTable[id_servicio],$A7,FacturasTable[moneda],"USD")) | H7: =IF($A7="","",IF($F7>0,"Con deuda pendiente","Sin deuda pendiente"))
B8: =IF($A8="","",_xlfn.XLOOKUP($A8,FacturasTable[id_servicio],FacturasTable[tipo_servicio],"")) | C8: =IF($A8="","",IF(COUNTIFS(FacturasTable[id_servicio],$A8,FacturasTable[moneda],"USD")>=COUNTIFS(FacturasTable[id_servicio],$A8,FacturasTable[moneda],"ARS"),"USD","ARS")) | D8: =IF($A8="","",COUNTIFS(FacturasTable[id_servicio],$A8)) | E8: =IF($A8="","",SUMIFS(FacturasTable[importe_equivalente_ars],FacturasTable[id_servicio],$A8)) | F8: =IF($A8="","",SUMIFS(FacturasTable[saldo_equivalente_ars],FacturasTable[id_servicio],$A8)) | G8: =IF($A8="","",SUMIFS(FacturasTable[importe_facturado],FacturasTable[id_servicio],$A8,FacturasTable[moneda],"USD")) | H8: =IF($A8="","",IF($F8>0,"Con deuda pendiente","Sin deuda pendiente"))
B9: =IF($A9="","",_xlfn.XLOOKUP($A9,FacturasTable[id_servicio],FacturasTable[tipo_servicio],"")) | C9: =IF($A9="","",IF(COUNTIFS(FacturasTable[id_servicio],$A9,FacturasTable[moneda],"USD")>=COUNTIFS(FacturasTable[id_servicio],$A9,FacturasTable[moneda],"ARS"),"USD","ARS")) | D9: =IF($A9="","",COUNTIFS(FacturasTable[id_servicio],$A9)) | E9: =IF($A9="","",SUMIFS(FacturasTable[importe_equivalente_ars],FacturasTable[id_servicio],$A9)) | F9: =IF($A9="","",SUMIFS(FacturasTable[saldo_equivalente_ars],FacturasTable[id_servicio],$A9)) | G9: =IF($A9="","",SUMIFS(FacturasTable[importe_facturado],FacturasTable[id_servicio],$A9,FacturasTable[moneda],"USD")) | H9: =IF($A9="","",IF($F9>0,"Con deuda pendiente","Sin deuda pendiente"))
B10: =IF($A10="","",_xlfn.XLOOKUP($A10,FacturasTable[id_servicio],FacturasTable[tipo_servicio],"")) | C10: =IF($A10="","",IF(COUNTIFS(FacturasTable[id_servicio],$A10,FacturasTable[moneda],"USD")>=COUNTIFS(FacturasTable[id_servicio],$A10,FacturasTable[moneda],"ARS"),"USD","ARS")) | D10: =IF($A10="","",COUNTIFS(FacturasTable[id_servicio],$A10)) | E10: =IF($A10="","",SUMIFS(FacturasTable[importe_equivalente_ars],FacturasTable[id_servicio],$A10)) | F10: =IF($A10="","",SUMIFS(FacturasTable[saldo_equivalente_ars],FacturasTable[id_servicio],$A10)) | G10: =IF($A10="","",SUMIFS(FacturasTable[importe_facturado],FacturasTable[id_servicio],$A10,FacturasTable[moneda],"USD")) | H10: =IF($A10="","",IF($F10>0,"Con deuda pendiente","Sin deuda pendiente"))
B11: =IF($A11="","",_xlfn.XLOOKUP($A11,FacturasTable[id_servicio],FacturasTable[tipo_servicio],"")) | C11: =IF($A11="","",IF(COUNTIFS(FacturasTable[id_servicio],$A11,FacturasTable[moneda],"USD")>=COUNTIFS(FacturasTable[id_servicio],$A11,FacturasTable[moneda],"ARS"),"USD","ARS")) | D11: =IF($A11="","",COUNTIFS(FacturasTable[id_servicio],$A11)) | E11: =IF($A11="","",SUMIFS(FacturasTable[importe_equivalente_ars],FacturasTable[id_servicio],$A11)) | F11: =IF($A11="","",SUMIFS(FacturasTable[saldo_equivalente_ars],FacturasTable[id_servicio],$A11)) | G11: =IF($A11="","",SUMIFS(FacturasTable[importe_facturado],FacturasTable[id_servicio],$A11,FacturasTable[moneda],"USD")) | H11: =IF($A11="","",IF($F11>0,"Con deuda pendiente","Sin deuda pendiente"))
B12: =IF($A12="","",_xlfn.XLOOKUP($A12,FacturasTable[id_servicio],FacturasTable[tipo_servicio],"")) | C12: =IF($A12="","",IF(COUNTIFS(FacturasTable[id_servicio],$A12,FacturasTable[moneda],"USD")>=COUNTIFS(FacturasTable[id_servicio],$A12,FacturasTable[moneda],"ARS"),"USD","ARS")) | D12: =IF($A12="","",COUNTIFS(FacturasTable[id_servicio],$A12)) | E12: =IF($A12="","",SUMIFS(FacturasTable[importe_equivalente_ars],FacturasTable[id_servicio],$A12)) | F12: =IF($A12="","",SUMIFS(FacturasTable[saldo_equivalente_ars],FacturasTable[id_servicio],$A12)) | G12: =IF($A12="","",SUMIFS(FacturasTable[importe_facturado],FacturasTable[id_servicio],$A12,FacturasTable[moneda],"USD")) | H12: =IF($A12="","",IF($F12>0,"Con deuda pendiente","Sin deuda pendiente"))
B13: =IF($A13="","",_xlfn.XLOOKUP($A13,FacturasTable[id_servicio],FacturasTable[tipo_servicio],"")) | C13: =IF($A13="","",IF(COUNTIFS(FacturasTable[id_servicio],$A13,FacturasTable[moneda],"USD")>=COUNTIFS(FacturasTable[id_servicio],$A13,FacturasTable[moneda],"ARS"),"USD","ARS")) | D13: =IF($A13="","",COUNTIFS(FacturasTable[id_servicio],$A13)) | E13: =IF($A13="","",SUMIFS(FacturasTable[importe_equivalente_ars],FacturasTable[id_servicio],$A13)) | F13: =IF($A13="","",SUMIFS(FacturasTable[saldo_equivalente_ars],FacturasTable[id_servicio],$A13)) | G13: =IF($A13="","",SUMIFS(FacturasTable[importe_facturado],FacturasTable[id_servicio],$A13,FacturasTable[moneda],"USD")) | H13: =IF($A13="","",IF($F13>0,"Con deuda pendiente","Sin deuda pendiente"))
B14: =IF($A14="","",_xlfn.XLOOKUP($A14,FacturasTable[id_servicio],FacturasTable[tipo_servicio],"")) | C14: =IF($A14="","",IF(COUNTIFS(FacturasTable[id_servicio],$A14,FacturasTable[moneda],"USD")>=COUNTIFS(FacturasTable[id_servicio],$A14,FacturasTable[moneda],"ARS"),"USD","ARS")) | D14: =IF($A14="","",COUNTIFS(FacturasTable[id_servicio],$A14)) | E14: =IF($A14="","",SUMIFS(FacturasTable[importe_equivalente_ars],FacturasTable[id_servicio],$A14)) | F14: =IF($A14="","",SUMIFS(FacturasTable[saldo_equivalente_ars],FacturasTable[id_servicio],$A14)) | G14: =IF($A14="","",SUMIFS(FacturasTable[importe_facturado],FacturasTable[id_servicio],$A14,FacturasTable[moneda],"USD")) | H14: =IF($A14="","",IF($F14>0,"Con deuda pendiente","Sin deuda pendiente"))
B15: =IF($A15="","",_xlfn.XLOOKUP($A15,FacturasTable[id_servicio],FacturasTable[tipo_servicio],"")) | C15: =IF($A15="","",IF(COUNTIFS(FacturasTable[id_servicio],$A15,FacturasTable[moneda],"USD")>=COUNTIFS(FacturasTable[id_servicio],$A15,FacturasTable[moneda],"ARS"),"USD","ARS")) | D15: =IF($A15="","",COUNTIFS(FacturasTable[id_servicio],$A15)) | E15: =IF($A15="","",SUMIFS(FacturasTable[importe_equivalente_ars],FacturasTable[id_servicio],$A15)) | F15: =IF($A15="","",SUMIFS(FacturasTable[saldo_equivalente_ars],FacturasTable[id_servicio],$A15)) | G15: =IF($A15="","",SUMIFS(FacturasTable[importe_facturado],FacturasTable[id_servicio],$A15,FacturasTable[moneda],"USD")) | H15: =IF($A15="","",IF($F15>0,"Con deuda pendiente","Sin deuda pendiente"))
B16: =IF($A16="","",_xlfn.XLOOKUP($A16,FacturasTable[id_servicio],FacturasTable[tipo_servicio],"")) | C16: =IF($A16="","",IF(COUNTIFS(FacturasTable[id_servicio],$A16,FacturasTable[moneda],"USD")>=COUNTIFS(FacturasTable[id_servicio],$A16,FacturasTable[moneda],"ARS"),"USD","ARS")) | D16: =IF($A16="","",COUNTIFS(FacturasTable[id_servicio],$A16)) | E16: =IF($A16="","",SUMIFS(FacturasTable[importe_equivalente_ars],FacturasTable[id_servicio],$A16)) | F16: =IF($A16="","",SUMIFS(FacturasTable[saldo_equivalente_ars],FacturasTable[id_servicio],$A16)) | G16: =IF($A16="","",SUMIFS(FacturasTable[importe_facturado],FacturasTable[id_servicio],$A16,FacturasTable[moneda],"USD")) | H16: =IF($A16="","",IF($F16>0,"Con deuda pendiente","Sin deuda pendiente"))
B17: =IF($A17="","",_xlfn.XLOOKUP($A17,FacturasTable[id_servicio],FacturasTable[tipo_servicio],"")) | C17: =IF($A17="","",IF(COUNTIFS(FacturasTable[id_servicio],$A17,FacturasTable[moneda],"USD")>=COUNTIFS(FacturasTable[id_servicio],$A17,FacturasTable[moneda],"ARS"),"USD","ARS")) | D17: =IF($A17="","",COUNTIFS(FacturasTable[id_servicio],$A17)) | E17: =IF($A17="","",SUMIFS(FacturasTable[importe_equivalente_ars],FacturasTable[id_servicio],$A17)) | F17: =IF($A17="","",SUMIFS(FacturasTable[saldo_equivalente_ars],FacturasTable[id_servicio],$A17)) | G17: =IF($A17="","",SUMIFS(FacturasTable[importe_facturado],FacturasTable[id_servicio],$A17,FacturasTable[moneda],"USD")) | H17: =IF($A17="","",IF($F17>0,"Con deuda pendiente","Sin deuda pendiente"))
B18: =IF($A18="","",_xlfn.XLOOKUP($A18,FacturasTable[id_servicio],FacturasTable[tipo_servicio],"")) | C18: =IF($A18="","",IF(COUNTIFS(FacturasTable[id_servicio],$A18,FacturasTable[moneda],"USD")>=COUNTIFS(FacturasTable[id_servicio],$A18,FacturasTable[moneda],"ARS"),"USD","ARS")) | D18: =IF($A18="","",COUNTIFS(FacturasTable[id_servicio],$A18)) | E18: =IF($A18="","",SUMIFS(FacturasTable[importe_equivalente_ars],FacturasTable[id_servicio],$A18)) | F18: =IF($A18="","",SUMIFS(FacturasTable[saldo_equivalente_ars],FacturasTable[id_servicio],$A18)) | G18: =IF($A18="","",SUMIFS(FacturasTable[importe_facturado],FacturasTable[id_servicio],$A18,FacturasTable[moneda],"USD")) | H18: =IF($A18="","",IF($F18>0,"Con deuda pendiente","Sin deuda pendiente"))

Sheet Tipo_Cambio
A1: mes | B1: tipo_cambio_referencia | C1: nota
A2: 45870 | B2: 1297 | C2: Tipo de cambio ficticio para portfolio
A3: 45901 | B3: 1330 | C3: Tipo de cambio ficticio para portfolio
A4: 45931 | B4: 1354 | C4: Tipo de cambio ficticio para portfolio
A5: 45962 | B5: 1398 | C5: Tipo de cambio ficticio para portfolio
A6: 45992 | B6: 1436 | C6: Tipo de cambio ficticio para portfolio
A7: 46023 | B7: 1457 | C7: Tipo de cambio ficticio para portfolio
A8: 46054 | B8: 1501 | C8: Tipo de cambio ficticio para portfolio
A9: 46082 | B9: 1554 | C9: Tipo de cambio ficticio para portfolio
A10: 46113 | B10: 1600 | C10: Tipo de cambio ficticio para portfolio
A11: 46143 | B11: 1653 | C11: Tipo de cambio ficticio para portfolio
A12: 46174 | B12: 1669 | C12: Tipo de cambio ficticio para portfolio
A13: 46204 | B13: 1716 | C13: Tipo de cambio ficticio para portfolio

Sheet Diccionario
A1: Campo | B1: Descripción | C1: Tipo / uso
A2: id_factura | B2: Identificador único de factura | C2: Texto
A3: fecha_emision | B3: Fecha de emisión de la factura | C3: Fecha
A4: fecha_vencimiento | B4: Fecha límite de pago | C4: Fecha
A5: fecha_pago | B5: Fecha de pago total o parcial | C5: Fecha
A6: cliente | B6: Cliente ficticio de la PyME | C6: Texto
A7: tipo_servicio | B7: Servicio facturado | C7: Categoría
A8: moneda | B8: Moneda original de la factura | C8: ARS / USD
A9: importe_facturado | B9: Importe original facturado | C9: Número
A10: importe_cobrado | B10: Importe cobrado a la fecha | C10: Número
A11: saldo_pendiente | B11: Importe facturado menos importe cobrado | C11: Fórmula
A12: tipo_cambio | B12: Tipo de cambio ficticio usado para convertir USD a ARS | C12: Número
... A20: vencida_si_no | B20: Marca facturas vencidas con saldo pendiente | C20: Fórmula

Sheet README
A1: Portfolio · Dashboard de cobranzas y facturación
A3: Objetivo | B3: Dataset ficticio para construir un dashboard de cobranzas y facturación orientado a PyMEs.
A4: Alcance | B4: Últimos 12 meses móviles, clientes del mismo tipo, facturación en ARS y USD.
A5: Flujo sugerido | B5: Python genera/enriquece datos → Excel revisa base → Power BI visualiza → Notion documenta el caso.
A6: Fecha de análisis | B6: 2026-07-01
A7: Hojas incluidas | B7: Resumen, Facturas, Clientes, Servicios, Tipo_Cambio, Diccionario.
A8: Nota | B8: Todos los datos son ficticios y fueron generados para uso de portfolio.
A10: Mejoras aplicadas | B10: Clientes y Servicios ahora se alimentan automáticamente desde Facturas con fórmulas.
A11: Selector de cliente | B11: En Clientes!I3 hay un desplegable por nombre de cliente con resumen automático de deuda y actividad.
A12: TopClientesTable | B12: En Resumen se agregó una nota de origen: sale de Facturas agrupadas por cliente.
A13: MVP | B13: Se mantiene un solo tipo de cliente para claridad; multi-rubro queda como mejora futura.
A14: Bimoneda | B14: El dataset conserva ARS y USD con equivalentes en ARS.
A15: Flujo | B15: Python/Excel como base de datos, y luego conexión a Power BI.
